Workbook

Sheet P&L
D1: 2022 | E1: 2022 | F1: 2022 | G1: 2023 | H1: TOTAL
D2: October | E2: November | F2: December | G2: January
B3: RM | C3: RM purchase @ std price | D3: =-'Purchases & PPV'!C17 -> -80425.5 | E3: =-'Purchases & PPV'!D17 -> -34200 | F3: =-'Purchases & PPV'!E17 -> -7300 | G3: =-'Purchases & PPV'!F17 -> -7503 | H3: =SUM(D3:G3) -> -129428.5
B4: RM | C4: PPV | D4: =-'Purchases & PPV'!C24 -> -5422 | E4: =-'Purchases & PPV'!D24 -> -1700 | F4: =-'Purchases & PPV'!E24 -> -650 | G4: =-'Purchases & PPV'!F24 -> 183 | H4: =SUM(D4:G4) -> -7589
B5: RM | C5: RM reception | D5: ='Purchases & PPV'!C17 -> 80425.5 | E5: ='Purchases & PPV'!D17 -> 34200 | F5: ='Purchases & PPV'!E17 -> 7300 | G5: ='Purchases & PPV'!F17 -> 7503 | H5: =SUM(D5:G5) -> 129428.5
A6: C | B6: RM | C6: RM consumption | D6: =SUMIFS(Movements!$K:$K,Movements!$A:$A,D$2,Movements!$G:$G,$A6,Movements!$D:$D,'P&L'!$B6) -> 0 | E6: =SUMIFS(Movements!$K:$K,Movements!$A:$A,E$2,Movements!$G:$G,$A6,Movements!$D:$D,'P&L'!$B6) -> -39852.853 | F6: =SUMIFS(Movements!$K:$K,Movements!$A:$A,F$2,Movements!$G:$G,$A6,Movements!$D:$D,'P&L'!$B6) -> -61895.887 | G6: =SUMIFS(Movements!$K:$K,Movements!$A:$A,G$2,Movements!$G:$G,$A6,Movements!$D:$D,'P&L'!$B6) -> -27801 | H6: =SUM(D6:G6) -> -129549.74
C7: consumption @ std | D7: =-'Formulation & overusage'!D106 -> 0 | E7: =-'Formulation & overusage'!E106 -> -39998.04 | F7: =-'Formulation & overusage'!F106 -> -61895.887 | G7: =-'Formulation & overusage'!G106 -> -27940.25
C8: Overusage variance | D8: =-'Formulation & overusage'!D103 -> 0 | E8: =-'Formulation & overusage'!E103 -> 180.3775 | F8: =-'Formulation & overusage'!F103 -> 55.2 | G8: =-'Formulation & overusage'!G103 -> 85.35
C9: Formulation variance | D9: =-'Formulation & overusage'!D100 -> 0 | E9: =-'Formulation & overusage'!E100 -> -35.19 | F9: =-'Formulation & overusage'!F100 -> -55.2 | G9: =-'Formulation & overusage'!G100 -> 53.9
A10: W | B10: RM | C10: RM write-off | D10: =SUMIFS(Movements!$K:$K,Movements!$A:$A,D$2,Movements!$G:$G,$A10,Movements!$D:$D,'P&L'!$B10) -> 0 | E10: =SUMIFS(Movements!$K:$K,Movements!$A:$A,E$2,Movements!$G:$G,$A10,Movements!$D:$D,'P&L'!$B10) -> -523.46 | F10: =SUMIFS(Movements!$K:$K,Movements!$A:$A,F$2,Movements!$G:$G,$A10,Movements!$D:$D,'P&L'!$B10) -> -199 | G10: =SUMIFS(Movements!$K:$K,Movements!$A:$A,G$2,Movements!$G:$G,$A10,Movements!$D:$D,'P&L'!$B10) -> -296 | H10: =SUM(D10:G10) -> -1018.46
A11: I | B11: RM | C11: RM stock adjusments | D11: =SUMIFS(Movements!$K:$K,Movements!$A:$A,D$2,Movements!$G:$G,$A11,Movements!$D:$D,'P&L'!$B11) -> 0 | E11: =SUMIFS(Movements!$K:$K,Movements!$A:$A,E$2,Movements!$G:$G,$A11,Movements!$D:$D,'P&L'!$B11) -> 0 | F11: =SUMIFS(Movements!$K:$K,Movements!$A:$A,F$2,Movements!$G:$G,$A11,Movements!$D:$D,'P&L'!$B11) -> -600 | G11: =SUMIFS(Movements!$K:$K,Movements!$A:$A,G$2,Movements!$G:$G,$A11,Movements!$D:$D,'P&L'!$B11) -> 0 | H11: =SUM(D11:G11) -> -600
B12: RM | C12: Stock reevaluation RM | D12: ='Stock reval'!E29 -> 5422 | E12: ='Stock reval'!F29 -> 767 | F12: ='Stock reval'!G29 -> -3927.7 | G12: ='Stock reval'!H29 -> -521.6 | H12: =SUM(D12:G12) -> 1739.7
A14: C | B14: SFG | C14: SFG consumption | D14: =SUMIFS(Movements!$K:$K,Movements!$A:$A,D$2,Movements!$G:$G,$A14,Movements!$D:$D,'P&L'!$B14) -> 0 | E14: =SUMIFS(Movements!$K:$K,Movements!$A:$A,E$2,Movements!$G:$G,$A14,Movements!$D:$D,'P&L'!$B14) -> -3005.8125 | F14: =SUMIFS(Movements!$K:$K,Movements!$A:$A,F$2,Movements!$G:$G,$A14,Movements!$D:$D,'P&L'!$B14) -> -4715 | G14: =SUMIFS(Movements!$K:$K,Movements!$A:$A,G$2,Movements!$G:$G,$A14,Movements!$D:$D,'P&L'!$B14) -> -3960.6 | H14: =SUM(D14:G14) -> -11681.413
B15: SFG | C15: consumption @ std | D15: =-'Formulation & overusage'!D107 -> 0 | E15: =-'Formulation & overusage'!E107 -> -3005.8125 | F15: =-'Formulation & overusage'!F107 -> -4715 | G15: =-'Formulation & overusage'!G107 -> -3921.96 | H15: ='Formulation & overusage'!H107 -> 0
B16: SFG | C16: Overusage variance | D16: =-'Formulation & overusage'!D104 -> 0 | E16: =-'Formulation & overusage'!E104 -> -29.325 | F16: =-'Formulation & overusage'!F104 -> -46 | G16: =-'Formulation & overusage'!G104 -> 0 | H16: =-'Formulation & overusage'!H104 -> 0
B17: SFG | C17: Formulation variance | D17: =-'Formulation & overusage'!D101 -> 0 | E17: =-'Formulation & overusage'!E101 -> 29.325 | F17: =-'Formulation & overusage'!F101 -> 46 | G17: =-'Formulation & overusage'!G101 -> -38.64 | H17: =-'Formulation & overusage'!H101 -> 0
A18: P | B18: SFG | C18: SFG output / production | D18: =SUMIFS(Movements!$K:$K,Movements!$A:$A,D$2,Movements!$G:$G,$A18,Movements!$D:$D,'P&L'!$B18) -> 0 | E18: =SUMIFS(Movements!$K:$K,Movements!$A:$A,E$2,Movements!$G:$G,$A18,Movements!$D:$D,'P&L'!$B18) -> 3162.5 | F18: =SUMIFS(Movements!$K:$K,Movements!$A:$A,F$2,Movements!$G:$G,$A18,Movements!$D:$D,'P&L'!$B18) -> 5895.1875 | G18: =SUMIFS(Movements!$K:$K,Movements!$A:$A,G$2,Movements!$G:$G,$A18,Movements!$D:$D,'P&L'!$B18) -> 2760 | H18: =SUM(D18:G18) -> 11817.688
A19: S | B19: SFG | C19: SFG write-off | D19: =SUMIFS(Movements!$K:$K,Movements!$A:$A,D$2,Movements!$G:$G,$A19,Movements!$D:$D,'P&L'!$B19) -> 0 | E19: =SUMIFS(Movements!$K:$K,Movements!$A:$A,E$2,Movements!$G:$G,$A19,Movements!$D:$D,'P&L'!$B19) -> 0 | F19: =SUMIFS(Movements!$K:$K,Movements!$A:$A,F$2,Movements!$G:$G,$A19,Movements!$D:$D,'P&L'!$B19) -> 0 | G19: =SUMIFS(Movements!$K:$K,Movements!$A:$A,G$2,Movements!$G:$G,$A19,Movements!$D:$D,'P&L'!$B19) -> 0 | H19: =SUM(D19:G19) -> 0
A20: I | B20: SFG | C20: SFG stock adjusments | D20: =SUMIFS(Movements!$K:$K,Movements!$A:$A,D$2,Movements!$G:$G,$A20,Movements!$D:$D,'P&L'!$B20) -> 0 | E20: =SUMIFS(Movements!$K:$K,Movements!$A:$A,E$2,Movements!$G:$G,$A20,Movements!$D:$D,'P&L'!$B20) -> 0 | F20: =SUMIFS(Movements!$K:$K,Movements!$A:$A,F$2,Movements!$G:$G,$A20,Movements!$D:$D,'P&L'!$B20) -> -86.25 | G20: =SUMIFS(Movements!$K:$K,Movements!$A:$A,G$2,Movements!$G:$G,$A20,Movements!$D:$D,'P&L'!$B20) -> 0 | H20: =SUM(D20:G20) -> -86.25
B21: SFG | C21: Stock reevaluation SFG | D21: ='Stock reval'!E34 -> 0 | E21: ='Stock reval'!F34 -> 0 | F21: ='Stock reval'!G34 -> -100.05 | G21: ='Stock reval'!H34 -> 50.025 | H21: =SUM(D21:G21) -> -50.025
A23: P | B23: FG | C23: FG output / production | D23: =SUMIFS(Movements!$K:$K,Movements!$A:$A,D$2,Movements!$G:$G,$A23,Movements!$D:$D,'P&L'!$B23) -> 0 | E23: =SUMIFS(Movements!$K:$K,Movements!$A:$A,E$2,Movements!$G:$G,$A23,Movements!$D:$D,'P&L'!$B23) -> 39841.353 | F23: =SUMIFS(Movements!$K:$K,Movements!$A:$A,F$2,Movements!$G:$G,$A23,Movements!$D:$D,'P&L'!$B23) -> 60715.7 | G23: =SUMIFS(Movements!$K:$K,Movements!$A:$A,G$2,Movements!$G:$G,$A23,Movements!$D:$D,'P&L'!$B23) -> 29102.21 | H23: =SUM(D23:G23) -> 129659.26
A24: D | B24: FG | C24: FG dispatch (sales) | D24: =SUMIFS(Movements!$K:$K,Movements!$A:$A,D$2,Movements!$G:$G,$A24,Movements!$D:$D,'P&L'!$B24) -> 0 | E24: =SUMIFS(Movements!$K:$K,Movements!$A:$A,E$2,Movements!$G:$G,$A24,Movements!$D:$D,'P&L'!$B24) -> -21146.825 | F24: =SUMIFS(Movements!$K:$K,Movements!$A:$A,F$2,Movements!$G:$G,$A24,Movements!$D:$D,'P&L'!$B24) -> -58251.475 | G24: =SUMIFS(Movements!$K:$K,Movements!$A:$A,G$2,Movements!$G:$G,$A24,Movements!$D:$D,'P&L'!$B24) -> -51857.84 | H24: =SUM(D24:G24) -> -131256.14
A25: W | B25: FG | C25: FG write-off | D25: =SUMIFS(Movements!$K:$K,Movements!$A:$A,D$2,Movements!$G:$G,$A25,Movements!$D:$D,'P&L'!$B25) -> 0 | E25: =SUMIFS(Movements!$K:$K,Movements!$A:$A,E$2,Movements!$G:$G,$A25,Movements!$D:$D,'P&L'!$B25) -> 0 | F25: =SUMIFS(Movements!$K:$K,Movements!$A:$A,F$2,Movements!$G:$G,$A25,Movements!$D:$D,'P&L'!$B25) -> 0 | G25: =SUMIFS(Movements!$K:$K,Movements!$A:$A,G$2,Movements!$G:$G,$A25,Movements!$D:$D,'P&L'!$B25) -> -85.35 | H25: =SUM(D25:G25) -> -85.35
A26: I | B26: FG | C26: FG stock adjusments | D26: =SUMIFS(Movements!$K:$K,Movements!$A:$A,D$2,Movements!$G:$G,$A26,Movements!$D:$D,'P&L'!$B26) -> 0 | E26: =SUMIFS(Movements!$K:$K,Movements!$A:$A,E$2,Movements!$G:$G,$A26,Movements!$D:$D,'P&L'!$B26) -> 0 | F26: =SUMIFS(Movements!$K:$K,Movements!$A:$A,F$2,Movements!$G:$G,$A26,Movements!$D:$D,'P&L'!$B26) -> -272.4775 | G26: =SUMIFS(Movements!$K:$K,Movements!$A:$A,G$2,Movements!$G:$G,$A26,Movements!$D:$D,'P&L'!$B26) -> 0 | H26: =SUM(D26:G26) -> -272.4775
B27: FG | C27: Stock reevaluation FG | D27: ='Stock reval'!E39 -> 0 | E27: ='Stock reval'!F39 -> 1491.04 | F27: ='Stock reval'!G39 -> 1145.71 | G27: ='Stock reval'!H39 -> -682.045 | H27: =SUM(D27:G27) -> 1954.705
C29: Slow moving provision | D29: ='Slow moving'!D36 -> 0 | E29: ='Slow moving'!E36 -> -3336.9438 | F29: ='Slow moving'!F36 -> 3336.9438 | G29: ='Slow moving'!G36 -> 0 | H29: =SUM(D29:G29) -> 0
C30: LOCOM provision | D30: =LOCOM!E14 -> 0 | E30: =LOCOM!F14 -> 0 | F30: =LOCOM!G14 -> -661.5 | G30: =LOCOM!H14 -> 661.5 | H30: =SUM(D30:G30) -> 0
I31: check
C32: TOTAL RM cost | D32: =SUM(D3:D30)-D6-D14 -> 0 | E32: =SUM(E3:E30)-E6-E14 -> -24304.001 | F32: =SUM(F3:F30)-F6-F14 -> -60265.799 | G32: =SUM(G3:G30)-G6-G14 -> -52447.7 | H32: =SUM(D32:G32) -> -137017.5 | I32: =H32+SUM('Purchases & PPV'!K17:N17) -> 0
C34: TOTAL SALES | E34: =Sales!C13 -> 35200 | F34: =Sales!D13 -> 89200 | G34: =Sales!E13 -> 77000 | H34: =SUM(D34:G34) -> 201400
C36: RM % sales | E36: =E32/E34 -> -0.69045458 | F36: =F32/F34 -> -0.67562555 | G36: =G32/G34 -> -0.68113896 | H36: =H32/H34 -> -0.68032522

Sheet IS

Sheet .

Sheet   

Sheet SL
B2: SL (storage location) | C2: SL description
B3: IN | C3: Inbound warehouse
B4: NP | C4: Nut plant
B5: Fint L | C5: Fint production line
B6: Step L | C6: Step production line
B7: PL | C7: Palletizer
B8: OUT | C8: Outbound warehouse

Sheet list of materials
E1: Std material cost
A2: Material number | B2: Material | C2: Mat type | D2: Mat type description | E2: 2022 | F2: 2023
A3: 120301 | B3: Fint | C3: FG | D3: Finished goods | E3: ='BOM & Std price'!M7 -> 27.24775 | F3: ='BOM & Std price'!P7 -> 29.2598
A4: 156212 | B4: Step | C4: FG | D4: Finished goods | E4: ='BOM & Std price'!M29 -> 25.945 | F4: ='BOM & Std price'!P29 -> 28.45
A5: 867156 | B5: Chocolate mass | C5: RM | D5: Raw material | E5: 28 | F5: 31
A6: 765190 | B6: Caramel | C6: RM | D6: Raw material | E6: 15 | F6: 16
A7: 657341 | B7: Raw Peanut | C7: RM | D7: Raw material | E7: 25 | F7: 24
A8: 876145 | B8: Fried Peanut | C8: SFG | D8: Semi-finished goods | E8: ='BOM & Std price'!M17 -> 28.75 | F8: ='BOM & Std price'!P17 -> 27.6
A9: 560196 | B9: Biscuit | C9: RM | D9: Raw material | E9: 25 | F9: 27

Sheet BOM & Std price
K1: Std cost breakdown | L1: 2022 | O1: 2023
C2: Product | D2: Fint | E2: ='list of materials'!A3 -> 120301 | L2: kg | M2: Std cost/kg | N2: LC | O2: kg | P2: Std cost/kg | Q2: LC
C3: Recipe per | D3: 1000 | E3: kg | K3: Chocolate mass | L3: =D7 -> 708 | M3: =VLOOKUP(K3,'list of materials'!B:E,4,0) -> 28 | N3: =M3*L3 -> 19824 | O3: =H7 -> 711 | P3: =VLOOKUP(K3,'list of materials'!B:F,5,0) -> 31 | Q3: =P3*O3 -> 22041
C4: Recipe type | D4: Std | K4: Fried Peanut | L4: =D8 -> 205 | M4: =VLOOKUP(K4,'list of materials'!B:E,4,0) -> 28.75 | N4: =M4*L4 -> 5893.75 | O4: =H8 -> 203 | P4: =VLOOKUP(K4,'list of materials'!B:F,5,0) -> 27.6 | Q4: =P4*O4 -> 5602.8
D5: kg / 1000 kg | K5: Caramel | L5: =D9 -> 102 | M5: =VLOOKUP(K5,'list of materials'!B:E,4,0) -> 15 | N5: =M5*L5 -> 1530 | O5: =H9 -> 101 | P5: =VLOOKUP(K5,'list of materials'!B:F,5,0) -> 16 | Q5: =P5*O5 -> 1616
A6: Mat type | B6: Alternative | C6: Mat number | D6: Std'22 | E6: Oct act | F6: Nov act | G6: Dec act | H6: Std'23 | I6: Jan act
A7: RM | B7: Chocolate mass | C7: ='list of materials'!A5 -> 867156 | D7: 708 | E7: 708 | F7: 711 | G7: 711 | H7: 711 | I7: 708 | K7: Material cost | M7: =N7/D3 -> 27.24775 | N7: =SUM(N3:N5) -> 27247.75 | P7: =Q7/D3 -> 29.2598 | Q7: =SUM(Q3:Q5) -> 29259.8
A8: SFG | B8: Fried Peanut | C8: ='list of materials'!A8 -> 876145 | D8: 205 | E8: 205 | F8: 203 | G8: 203 | H8: 203 | I8: 205 | K8: Variable conv cost | M8: Direct labor | N8: 2000 | P8: Direct labor | Q8: 2000
A9: RM | B9: Caramel | C9: ='list of materials'!A6 -> 765190 | D9: 102 | E9: 102 | F9: 101 | G9: 101 | H9: 101 | I9: 102 | K9: Variable conv cost | M9: Energy | N9: 1000 | P9: Energy | Q9: 1000
B10: Total | D10: =SUM(D7:D9) -> 1015 | E10: =SUM(E7:E9) -> 1015 | F10: =SUM(F7:F9) -> 1015 | G10: =SUM(G7:G9) -> 1015 | H10: =SUM(H7:H9) -> 1015 | I10: =SUM(I7:I9) -> 1015 | K10: Fixed MFG ОHs | M10: MFG Fixed | N10: 800 | P10: MFG Fixed | Q10: 800
B11: Designed process loss | D11: =D10/$D$3-1 -> 0.015 | E11: =E10/$D$3-1 -> 0.015 | F11: =F10/$D$3-1 -> 0.015 | G11: =G10/$D$3-1 -> 0.015 | H11: =H10/$D$3-1 -> 0.015 | I11: =I10/$D$3-1 -> 0.015 | K11: Standard cost | M11: =N11/D3 -> 31.04775 | N11: =SUM(N7:N10) -> 31047.75 | P11: =Q11/D3 -> 33.0598 | Q11: =SUM(Q7:Q10) -> 33059.8
C13: Product | D13: Fried Peanut | K13: Std cost breakdown | L13: 2022 | O13: 2023
C14: Recipe per | D14: 1000 | E14: kg | L14: kg | M14: Std cost/kg | N14: LC | O14: kg | P14: Std cost/kg | Q14: LC
C15: Recipe type | D15: Std | K15: Raw Peanut | L15: =D18 -> 1150 | M15: =VLOOKUP(K15,'list of materials'!B:E,4,0) -> 25 | N15: =M15*L15 -> 28750 | O15: =H18 -> 1150 | P15: =VLOOKUP(K15,'list of materials'!B:F,5,0) -> 24 | Q15: =P15*O15 -> 27600
D16: kg / 1000 kg
A17: Mat type | B17: Alternative | C17: Mat number | D17: Std'22 | E17: Oct act | F17: Nov act | G17: Dec act | H17: Std'23 | I17: Jan act | K17: Material cost | M17: =N17/D14 -> 28.75 | N17: =SUM(N13:N15) -> 28750 | P17: =Q17/D14 -> 27.6 | Q17: =SUM(Q13:Q15) -> 27600
A18: RM | B18: Raw Peanut | C18: ='list of materials'!A7 -> 657341 | D18: 1150 | E18: 1150 | F18: 1150 | G18: 1150 | H18: 1150 | I18: 1150 | K18: Variable conv cost | M18: Direct labor | N18: 500 | P18: Direct labor | Q18: 500
B19: Total | D19: =SUM(D18) -> 1150 | E19: =SUM(E18) -> 1150 | F19: =SUM(F18) -> 1150 | G19: =SUM(G18) -> 1150 | H19: =SUM(H18) -> 1150 | I19: =SUM(I18) -> 1150 | K19: Variable conv cost | M19: Energy | N19: 400 | P19: Energy | Q19: 400
B20: Designed process loss | D20: =D19/$D$14-1 -> 0.15 | E20: =E19/$D$14-1 -> 0.15 | F20: =F19/$D$14-1 -> 0.15 | G20: =G19/$D$14-1 -> 0.15 | H20: =H19/$D$14-1 -> 0.15 | I20: =I19/$D$14-1 -> 0.15 | K20: Fixed MFG ОHs | M20: MFG Fixed | N20: 200 | P20: MFG Fixed | Q20: 200
K21: Standard cost | M21: =N21/D14 -> 29.85 | N21: =SUM(N17:N20) -> 29850 | P21: =Q21/D14 -> 28.7 | Q21: =SUM(Q17:Q20) -> 28700
C23: Product | D23: Step | K23: Std cost breakdown | L23: 2022 | O23: 2023
C24: Recipe per | D24: 1000 | E24: kg | L24: kg | M24: Std cost/kg | N24: LC | O24: kg | P24: Std cost/kg | Q24: LC
C25: Recipe type | D25: Std | K25: Chocolate mass | L25: =D29 -> 590 | M25: =VLOOKUP(K25,'list of materials'!B:E,4,0) -> 28 | N25: =M25*L25 -> 16520 | O25: =H29 -> 590 | P25: =VLOOKUP(K25,'list of materials'!B:F,5,0) -> 31 | Q25: =P25*O25 -> 18290
K26: Biscuit | L26: =D30 -> 320 | M26: =VLOOKUP(K26,'list of materials'!B:E,4,0) -> 25 | N26: =M26*L26 -> 8000 | O26: =H30 -> 320 | P26: =VLOOKUP(K26,'list of materials'!B:F,5,0) -> 27 | Q26: =P26*O26 -> 8640
D27: kg / 1000 kg | K27: Caramel | L27: =D31 -> 95 | M27: =VLOOKUP(K27,'list of materials'!B:E,4,0) -> 15 | N27: =M27*L27 -> 1425 | O27: =H31 -> 95 | P27: =VLOOKUP(K27,'list of materials'!B:F,5,0) -> 16 | Q27: =P27*O27 -> 1520
A28: Mat type | B28: Alternative | C28: Mat number | D28: Std'22 | E28: Oct act | F28: Nov act | G28: Dec act | H28: Std'23 | I28: Jan act
A29: RM | B29: Chocolate mass | C29: ='list of materials'!A5 -> 867156 | D29: 590 | E29: 590 | F29: 590 | G29: 590 | H29: 590 | I29: 590 | K29: Material cost | M29: =N29/D24 -> 25.945 | N29: =SUM(N25:N27) -> 25945 | P29: =Q29/D24 -> 28.45 | Q29: =SUM(Q25:Q27) -> 28450
A30: RM | B30: Biscuit | C30: ='list of materials'!A9 -> 560196 | D30: 320 | E30: 320 | F30: 320 | G30: 320 | H30: 320 | I30: 320 | K30: Variable conv cost | M30: Direct labor | N30: 2200 | P30: Direct labor | Q30: 2200
A31: RM | B31: Caramel | C31: ='list of materials'!A6 -> 765190 | D31: 95 | E31: 95 | F31: 95 | G31: 95 | H31: 95 | I31: 95 | K31: Variable conv cost | M31: Energy | N31: 900 | P31: Energy | Q31: 900
B32: Total | D32: =SUM(D29:D31) -> 1005 | E32: =SUM(E29:E31) -> 1005 | F32: =SUM(F29:F31) -> 1005 | G32: =SUM(G29:G31) -> 1005 | H32: =SUM(H29:H31) -> 1005 | I32: =SUM(I29:I31) -> 1005 | K32: Fixed MFG ОHs | M32: MFG Fixed | N32: 800 | P32: MFG Fixed | Q32: 800
B33: Designed process loss | D33: =D32/$D$24-1 -> 0.005 | E33: =E32/$D$24-1 -> 0.005 | F33: =F32/$D$24-1 -> 0.005 | G33: =G32/$D$24-1 -> 0.005 | H33: =H32/$D$24-1 -> 0.005 | I33: =I32/$D$24-1 -> 0.005 | K33: Standard cost | M33: =N33/D24 -> 29.845 | N33: =SUM(N29:N32) -> 29845 | P33: =Q33/D24 -> 32.35 | Q33: =SUM(Q29:Q32) -> 32350

Sheet MvT types
B2: Movement | C2: Movement description
B3: R | C3: reception
B4: C | C4: consumption
B5: M | C5: internal movement
B6: P | C6: goods production
B7: W | C7: Write-off
B8: I | C8: Inventory stock-take
B9: D | C9: dispatch

Sheet Movements
A1: Month | B1: Material | C1: Mat descr | D1: Material type | E1: SL | F1: Storage location | G1: Movement | H1: Movement type | I1: Quantity | J1: Std price | K1: Amount local currency
A2: October | B2: 867156 | C2: =VLOOKUP(B2,'list of materials'!A:B,2,0) -> Chocolate mass | D2: =VLOOKUP(B2,'list of materials'!A:C,3,0) -> RM | E2: IN | F2: =VLOOKUP(E2,SL!B:C,2,0) -> Inbound warehouse | G2: R | H2: =VLOOKUP(G2,'MvT types'!B:C,2,0) -> reception | I2: 2481 | J2: =VLOOKUP(B2,'list of materials'!A:E,5,0) -> 28 | K2: =I2*J2 -> 69468
A3: October | B3: 765190 | C3: =VLOOKUP(B3,'list of materials'!A:B,2,0) -> Caramel | D3: =VLOOKUP(B3,'list of materials'!A:C,3,0) -> RM | E3: IN | F3: =VLOOKUP(E3,SL!B:C,2,0) -> Inbound warehouse | G3: R | H3: =VLOOKUP(G3,'MvT types'!B:C,2,0) -> reception | I3: 198 | J3: =VLOOKUP(B3,'list of materials'!A:E,5,0) -> 15 | K3: =I3*J3 -> 2970
A4: October | B4: 657341 | C4: =VLOOKUP(B4,'list of materials'!A:B,2,0) -> Raw Peanut | D4: =VLOOKUP(B4,'list of materials'!A:C,3,0) -> RM | E4: IN | F4: =VLOOKUP(E4,SL!B:C,2,0) -> Inbound warehouse | G4: R | H4: =VLOOKUP(G4,'MvT types'!B:C,2,0) -> reception | I4: 89.5 | J4: =VLOOKUP(B4,'list of materials'!A:E,5,0) -> 25 | K4: =I4*J4 -> 2237.5
A5: October | B5: 560196 | C5: =VLOOKUP(B5,'list of materials'!A:B,2,0) -> Biscuit | D5: =VLOOKUP(B5,'list of materials'!A:C,3,0) -> RM | E5: IN | F5: =VLOOKUP(E5,SL!B:C,2,0) -> Inbound warehouse | G5: R | H5: =VLOOKUP(G5,'MvT types'!B:C,2,0) -> reception | I5: 330 | J5: =VLOOKUP(B5,'list of materials'!A:E,5,0) -> 25 | K5: =I5*J5 -> 8250
A6: October | B6: 560196 | C6: =VLOOKUP(B6,'list of materials'!A:B,2,0) -> Biscuit | D6: =VLOOKUP(B6,'list of materials'!A:C,3,0) -> RM | E6: IN | F6: =VLOOKUP(E6,SL!B:C,2,0) -> Inbound warehouse | G6: R | H6: =VLOOKUP(G6,'MvT types'!B:C,2,0) -> reception | I6: -100 | J6: =VLOOKUP(B6,'list of materials'!A:E,5,0) -> 25 | K6: =I6*J6 -> -2500
A7: November | B7: 120301 | C7: =VLOOKUP(B7,'list of materials'!A:B,2,0) -> Fint | D7: =VLOOKUP(B7,'list of materials'!A:C,3,0) -> FG | E7: PL | F7: =VLOOKUP(E7,SL!B:C,2,0) -> Palletizer | G7: P | H7: =VLOOKUP(G7,'MvT types'!B:C,2,0) -> goods production | I7: 510 | J7: =VLOOKUP(B7,'list of materials'!A:E,5,0) -> 27.24775 | K7: =I7*J7 -> 13896.352
A8: November | B8: 156212 | C8: =VLOOKUP(B8,'list of materials'!A:B,2,0) -> Step | D8: =VLOOKUP(B8,'list of materials'!A:C,3,0) -> FG | E8: PL | F8: =VLOOKUP(E8,SL!B:C,2,0) -> Palletizer | G8: P | H8: =VLOOKUP(G8,'MvT types'!B:C,2,0) -> goods production | I8: 1000 | J8: =VLOOKUP(B8,'list of materials'!A:E,5,0) -> 25.945 | K8: =I8*J8 -> 25945
A9: November | B9: 876145 | C9: =VLOOKUP(B9,'list of materials'!A:B,2,0) -> Fried Peanut | D9: =VLOOKUP(B9,'list of materials'!A:C,3,0) -> SFG | E9: NP | F9: =VLOOKUP(E9,SL!B:C,2,0) -> Nut plant | G9: P | H9: =VLOOKUP(G9,'MvT types'!B:C,2,0) -> goods production | I9: 110 | J9: =VLOOKUP(B9,'list of materials'!A:E,5,0) -> 28.75 | K9: =I9*J9 -> 3162.5
A10: December | B10: 120301 | C10: =VLOOKUP(B10,'list of materials'!A:B,2,0) -> Fint | D10: =VLOOKUP(B10,'list of materials'!A:C,3,0) -> FG | E10: PL | F10: =VLOOKUP(E10,SL!B:C,2,0) -> Palletizer | G10: P | H10: =VLOOKUP(G10,'MvT types'!B:C,2,0) -> goods production | I10: 800 | J10: =VLOOKUP(B10,'list of materials'!A:E,5,0) -> 27.24775 | K10: =I10*J10 -> 21798.2
A11: December | B11: 156212 | C11: =VLOOKUP(B11,'list of materials'!A:B,2,0) -> Step | D11: =VLOOKUP(B11,'list of materials'!A:C,3,0) -> FG | E11: PL | F11: =VLOOKUP(E11,SL!B:C,2,0) -> Palletizer | G11: P | H11: =VLOOKUP(G11,'MvT types'!B:C,2,0) -> goods production | I11: 1500 | J11: =VLOOKUP(B11,'list of materials'!A:E,5,0) -> 25.945 | K11: =I11*J11 -> 38917.5
A12: December | B12: 876145 | C12: =VLOOKUP(B12,'list of materials'!A:B,2,0) -> Fried Peanut | D12: =VLOOKUP(B12,'list of materials'!A:C,3,0) -> SFG | E12: NP | F12: =VLOOKUP(E12,SL!B:C,2,0) -> Nut plant | G12: P | H12: =VLOOKUP(G12,'MvT types'!B:C,2,0) -> goods production | I12: 205.05 | J12: =VLOOKUP(B12,'list of materials'!A:E,5,0) -> 28.75 | K12: =I12*J12 -> 5895.1875
A13: January | B13: 120301 | C13: =VLOOKUP(B13,'list of materials'!A:B,2,0) -> Fint | D13: =VLOOKUP(B13,'list of materials'!A:C,3,0) -> FG | E13: PL | F13: =VLOOKUP(E13,SL!B:C,2,0) -> Palletizer | G13: P | H13: =VLOOKUP(G13,'MvT types'!B:C,2,0) -> goods production | I13: 700 | J13: =VLOOKUP(B13,'list of materials'!A:F,6,0) -> 29.2598 | K13: =I13*J13 -> 20481.86
A14: January | B14: 156212 | C14: =VLOOKUP(B14,'list of materials'!A:B,2,0) -> Step | D14: =VLOOKUP(B14,'list of materials'!A:C,3,0) -> FG | E14: PL | F14: =VLOOKUP(E14,SL!B:C,2,0) -> Palletizer | G14: P | H14: =VLOOKUP(G14,'MvT types'!B:C,2,0) -> goods production | I14: 303 | J14: =VLOOKUP(B14,'list of materials'!A:F,6,0) -> 28.45 | K14: =I14*J14 -> 8620.35
A15: January | B15: 876145 | C15: =VLOOKUP(B15,'list of materials'!A:B,2,0) -> Fried Peanut | D15: =VLOOKUP(B15,'list of materials'!A:C,3,0) -> SFG | E15: NP | F15: =VLOOKUP(E15,SL!B:C,2,0) -> Nut plant | G15: P | H15: =VLOOKUP(G15,'MvT types'!B:C,2,0) -> goods production | I15: 100 | J15: =VLOOKUP(B15,'list of materials'!A:F,6,0) -> 27.6 | K15: =I15*J15 -> 2760
A16: November | B16: 120301 | C16: =VLOOKUP(B16,'list of materials'!A:B,2,0) -> Fint | D16: =VLOOKUP(B16,'list of materials'!A:C,3,0) -> FG | E16: PL | F16: =VLOOKUP(E16,SL!B:C,2,0) -> Palletizer | G16: M | H16: =VLOOKUP(G16,'MvT types'!B:C,2,0) -> internal movement | I16: -510 | J16: =VLOOKUP(B16,'list of materials'!A:E,5,0) -> 27.24775 | K16: =I16*J16 -> -13896.352
A17: November | B17: 156212 | C17: =VLOOKUP(B17,'list of materials'!A:B,2,0) -> Step | D17: =VLOOKUP(B17,'list of materials'!A:C,3,0) -> FG | E17: PL | F17: =VLOOKUP(E17,SL!B:C,2,0) -> Palletizer | G17: M | H17: =VLOOKUP(G17,'MvT types'!B:C,2,0) -> internal movement | I17: -1000 | J17: =VLOOKUP(B17,'list of materials'!A:E,5,0) -> 25.945 | K17: =I17*J17 -> -25945
A18: December | B18: 120301 | C18: =VLOOKUP(B18,'list of materials'!A:B,2,0) -> Fint | D18: =VLOOKUP(B18,'list of materials'!A:C,3,0) -> FG | E18: PL | F18: =VLOOKUP(E18,SL!B:C,2,0) -> Palletizer | G18: M | H18: =VLOOKUP(G18,'MvT types'!B:C,2,0) -> internal movement | I18: -800 | J18: =VLOOKUP(B18,'list of materials'!A:E,5,0) -> 27.24775 | K18: =I18*J18 -> -21798.2
A19: December | B19: 156212 | C19: =VLOOKUP(B19,'list of materials'!A:B,2,0) -> Step | D19: =VLOOKUP(B19,'list of materials'!A:C,3,0) -> FG | E19: PL | F19: =VLOOKUP(E19,SL!B:C,2,0) -> Palletizer | G19: M | H19: =VLOOKUP(G19,'MvT types'!B:C,2,0) -> internal movement | I19: -1500 | J19: =VLOOKUP(B19,'list of materials'!A:E,5,0) -> 25.945 | K19: =I19*J19 -> -38917.5
A20: January | B20: 120301 | C20: =VLOOKUP(B20,'list of materials'!A:B,2,0) -> Fint | D20: =VLOOKUP(B20,'list of materials'!A:C,3,0) -> FG | E20: PL | F20: =VLOOKUP(E20,SL!B:C,2,0) -> Palletizer | G20: M | H20: =VLOOKUP(G20,'MvT types'!B:C,2,0) -> internal movement | I20: -700 | J20: =VLOOKUP(B20,'list of materials'!A:F,6,0) -> 29.2598 | K20: =I20*J20 -> -20481.86
A21: January | B21: 156212 | C21: =VLOOKUP(B21,'list of materials'!A:B,2,0) -> Step | D21: =VLOOKUP(B21,'list of materials'!A:C,3,0) -> FG | E21: PL | F21: =VLOOKUP(E21,SL!B:C,2,0) -> Palletizer | G21: M | H21: =VLOOKUP(G21,'MvT types'!B:C,2,0) -> internal movement | I21: -303 | J21: =VLOOKUP(B21,'list of materials'!A:F,6,0) -> 28.45 | K21: =I21*J21 -> -8620.35
A22: November | B22: 120301 | C22: =VLOOKUP(B22,'list of materials'!A:B,2,0) -> Fint | D22: =VLOOKUP(B22,'list of materials'!A:C,3,0) -> FG | E22: OUT | F22: =VLOOKUP(E22,SL!B:C,2,0) -> Outbound warehouse | G22: M | H22: =VLOOKUP(G22,'MvT types'!B:C,2,0) -> internal movement | I22: 510 | J22: =VLOOKUP(B22,'list of materials'!A:E,5,0) -> 27.24775 | K22: =I22*J22 -> 13896.352
A23: November | B23: 156212 | C23: =VLOOKUP(B23,'list of materials'!A:B,2,0) -> Step | D23: =VLOOKUP(B23,'list of materials'!A:C,3,0) -> FG | E23: OUT | F23: =VLOOKUP(E23,SL!B:C,2,0) -> Outbound warehouse | G23: M | H23: =VLOOKUP(G23,'MvT types'!B:C,2,0) -> internal movement | I23: 1000 | J23: =VLOOKUP(B23,'list of materials'!A:E,5,0) -> 25.945 | K23: =I23*J23 -> 25945
A24: December | B24: 120301 | C24: =VLOOKUP(B24,'list of materials'!A:B,2,0) -> Fint | D24: =VLOOKUP(B24,'list of materials'!A:C,3,0) -> FG | E24: OUT | F24: =VLOOKUP(E24,SL!B:C,2,0) -> Outbound warehouse | G24: M | H24: =VLOOKUP(G24,'MvT types'!B:C,2,0) -> internal movement | I24: 800 | J24: =VLOOKUP(B24,'list of materials'!A:E,5,0) -> 27.24775 | K24: =I24*J24 -> 21798.2
A25: December | B25: 156212 | C25: =VLOOKUP(B25,'list of materials'!A:B,2,0) -> Step | D25: =VLOOKUP(B25,'list of materials'!A:C,3,0) -> FG | E25: OUT | F25: =VLOOKUP(E25,SL!B:C,2,0) -> Outbound warehouse | G25: M | H25: =VLOOKUP(G25,'MvT types'!B:C,2,0) -> internal movement | I25: 1500 | J25: =VLOOKUP(B25,'list of materials'!A:E,5,0) -> 25.945 | K25: =I25*J25 -> 38917.5
A26: January | B26: 120301 | C26: =VLOOKUP(B26,'list of materials'!A:B,2,0) -> Fint | D26: =VLOOKUP(B26,'list of materials'!A:C,3,0) -> FG | E26: OUT | F26: =VLOOKUP(E26,SL!B:C,2,0) -> Outbound warehouse | G26: M | H26: =VLOOKUP(G26,'MvT types'!B:C,2,0) -> internal movement | I26: 700 | J26: =VLOOKUP(B26,'list of materials'!A:F,6,0) -> 29.2598 | K26: =I26*J26 -> 20481.86
A27: January | B27: 156212 | C27: =VLOOKUP(B27,'list of materials'!A:B,2,0) -> Step | D27: =VLOOKUP(B27,'list of materials'!A:C,3,0) -> FG | E27: OUT | F27: =VLOOKUP(E27,SL!B:C,2,0) -> Outbound warehouse | G27: M | H27: =VLOOKUP(G27,'MvT types'!B:C,2,0) -> internal movement | I27: 303 | J27: =VLOOKUP(B27,'list of materials'!A:F,6,0) -> 28.45 | K27: =I27*J27 -> 8620.35
A28: November | B28: 120301 | C28: =VLOOKUP(B28,'list of materials'!A:B,2,0) -> Fint | D28: =VLOOKUP(B28,'list of materials'!A:C,3,0) -> FG | E28: OUT | F28: =VLOOKUP(E28,SL!B:C,2,0) -> Outbound warehouse | G28: D | H28: =VLOOKUP(G28,'MvT types'!B:C,2,0) -> dispatch | I28: -300 | J28: =VLOOKUP(B28,'list of materials'!A:E,5,0) -> 27.24775 | K28: =I28*J28 -> -8174.325
A29: November | B29: 156212 | C29: =VLOOKUP(B29,'list of materials'!A:B,2,0) -> Step | D29: =VLOOKUP(B29,'list of materials'!A:C,3,0) -> FG | E29: OUT | F29: =VLOOKUP(E29,SL!B:C,2,0) -> Outbound warehouse | G29: D | H29: =VLOOKUP(G29,'MvT types'!B:C,2,0) -> dispatch | I29: -500 | J29: =VLOOKUP(B29,'list of materials'!A:E,5,0) -> 25.945 | K29: =I29*J29 -> -12972.5
A30: December | B30: 120301 | C30: =VLOOKUP(B30,'list of materials'!A:B,2,0) -> Fint | D30: =VLOOKUP(B30,'list of materials'!A:C,3,0) -> FG | E30: OUT | F30: =VLOOKUP(E30,SL!B:C,2,0) -> Outbound warehouse | G30: D | H30: =VLOOKUP(G30,'MvT types'!B:C,2,0) -> dispatch | I30: -900 | J30: =VLOOKUP(B30,'list of materials'!A:E,5,0) -> 27.24775 | K30: =I30*J30 -> -24522.975
A31: December | B31: 156212 | C31: =VLOOKUP(B31,'list of materials'!A:B,2,0) -> Step | D31: =VLOOKUP(B31,'list of materials'!A:C,3,0) -> FG | E31: OUT | F31: =VLOOKUP(E31,SL!B:C,2,0) -> Outbound warehouse | G31: D | H31: =VLOOKUP(G31,'MvT types'!B:C,2,0) -> dispatch | I31: -1300 | J31: =VLOOKUP(B31,'list of materials'!A:E,5,0) -> 25.945 | K31: =I31*J31 -> -33728.5
A32: January | B32: 120301 | C32: =VLOOKUP(B32,'list of materials'!A:B,2,0) -> Fint | D32: =VLOOKUP(B32,'list of materials'!A:C,3,0) -> FG | E32: OUT | F32: =VLOOKUP(E32,SL!B:C,2,0) -> Outbound warehouse | G32: D | H32: =VLOOKUP(G32,'MvT types'!B:C,2,0) -> dispatch | I32: -800 | J32: =VLOOKUP(B32,'list of materials'!A:F,6,0) -> 29.2598 | K32: =I32*J32 -> -23407.84
A33: January | B33: 156212 | C33: =VLOOKUP(B33,'list of materials'!A:B,2,0) -> Step | D33: =VLOOKUP(B33,'list of materials'!A:C,3,0) -> FG | E33: OUT | F33: =VLOOKUP(E33,SL!B:C,2,0) -> Outbound warehouse | G33: D | H33: =VLOOKUP(G33,'MvT types'!B:C,2,0) -> dispatch | I33: -1000 | J33: =VLOOKUP(B33,'list of materials'!A:F,6,0) -> 28.45 | K33: =I33*J33 -> -28450
A34: November | B34: 876145 | C34: =VLOOKUP(B34,'list of materials'!A:B,2,0) -> Fried Peanut | D34: =VLOOKUP(B34,'list of materials'!A:C,3,0) -> SFG | E34: NP | F34: =VLOOKUP(E34,SL!B:C,2,0) -> Nut plant | G34: M | H34: =VLOOKUP(G34,'MvT types'!B:C,2,0) -> internal movement | I34: -110 | J34: =VLOOKUP(B34,'list of materials'!A:E,5,0) -> 28.75 | K34: =I34*J34 -> -3162.5
A35: December | B35: 876145 | C35: =VLOOKUP(B35,'list of materials'!A:B,2,0) -> Fried Peanut | D35: =VLOOKUP(B35,'list of materials'!A:C,3,0) -> SFG | E35: NP | F35: =VLOOKUP(E35,SL!B:C,2,0) -> Nut plant | G35: M | H35: =VLOOKUP(G35,'MvT types'!B:C,2,0) -> internal movement | I35: -205.05 | J35: =VLOOKUP(B35,'list of materials'!A:E,5,0) -> 28.75 | K35: =I35*J35 -> -5895.1875
A36: January | B36: 876145 | C36: =VLOOKUP(B36,'list of materials'!A:B,2,0) -> Fried Peanut | D36: =VLOOKUP(B36,'list of materials'!A:C,3,0) -> SFG | E36: NP | F36: =VLOOKUP(E36,SL!B:C,2,0) -> Nut plant | G36: M | H36: =VLOOKUP(G36,'MvT types'!B:C,2,0) -> internal movement | I36: -100 | J36: =VLOOKUP(B36,'list of materials'!A:F,6,0) -> 27.6 | K36: =I36*J36 -> -2760
A37: November | B37: 876145 | C37: =VLOOKUP(B37,'list of materials'!A:B,2,0) -> Fried Peanut | D37: =VLOOKUP(B37,'list of materials'!A:C,3,0) -> SFG | E37: Fint L | F37: =VLOOKUP(E37,SL!B:C,2,0) -> Fint production line | G37: M | H37: =VLOOKUP(G37,'MvT types'!B:C,2,0) -> internal movement | I37: 110 | J37: =VLOOKUP(B37,'list of materials'!A:E,5,0) -> 28.75 | K37: =I37*J37 -> 3162.5
A38: December | B38: 876145 | C38: =VLOOKUP(B38,'list of materials'!A:B,2,0) -> Fried Peanut | D38: =VLOOKUP(B38,'list of materials'!A:C,3,0) -> SFG | E38: Fint L | F38: =VLOOKUP(E38,SL!B:C,2,0) -> Fint production line | G38: M | H38: =VLOOKUP(G38,'MvT types'!B:C,2,0) -> internal movement | I38: 205.05 | J38: =VLOOKUP(B38,'list of materials'!A:E,5,0) -> 28.75 | K38: =I38*J38 -> 5895.1875
A39: January | B39: 876145 | C39: =VLOOKUP(B39,'list of materials'!A:B,2,0) -> Fried Peanut | D39: =VLOOKUP(B39,'list of materials'!A:C,3,0) -> SFG | E39: Fint L | F39: =VLOOKUP(E39,SL!B:C,2,0) -> Fint production line | G39: M | H39: =VLOOKUP(G39,'MvT types'!B:C,2,0) -> internal movement | I39: 100 | J39: =VLOOKUP(B39,'list of materials'!A:F,6,0) -> 27.6 | K39: =I39*J39 -> 2760
A40: November | B40: 867156 | C40: =VLOOKUP(B40,'list of materials'!A:B,2,0) -> Chocolate mass | D40: =VLOOKUP(B40,'list of materials'!A:C,3,0) -> RM | E40: Fint L | F40: =VLOOKUP(E40,SL!B:C,2,0) -> Fint production line | G40: C | H40: =VLOOKUP(G40,'MvT types'!B:C,2,0) -> consumption | I40: -361.08 | J40: =VLOOKUP(B40,'list of materials'!A:E,5,0) -> 28 | K40: =I40*J40 -> -10110.24
A41: November | B41: 876145 | C41: =VLOOKUP(B41,'list of materials'!A:B,2,0) -> Fried Peanut | D41: =VLOOKUP(B41,'list of materials'!A:C,3,0) -> SFG | E41: Fint L | F41: =VLOOKUP(E41,SL!B:C,2,0) -> Fint production line | G41: C | H41: =VLOOKUP(G41,'MvT types'!B:C,2,0) -> consumption | I41: -104.55 | J41: =VLOOKUP(B41,'list of materials'!A:E,5,0) -> 28.75 | K41: =I41*J41 -> -3005.8125
A42: November | B42: 765190 | C42: =VLOOKUP(B42,'list of materials'!A:B,2,0) -> Caramel | D42: =VLOOKUP(B42,'list of materials'!A:C,3,0) -> RM | E42: Fint L | F42: =VLOOKUP(E42,SL!B:C,2,0) -> Fint production line | G42: C | H42: =VLOOKUP(G42,'MvT types'!B:C,2,0) -> consumption | I42: -52.02 | J42: =VLOOKUP(B42,'list of materials'!A:E,5,0) -> 15 | K42: =I42*J42 -> -780.3
A43: December | B43: 867156 | C43: =VLOOKUP(B43,'list of materials'!A:B,2,0) -> Chocolate mass | D43: =VLOOKUP(B43,'list of materials'!A:C,3,0) -> RM | E43: Fint L | F43: =VLOOKUP(E43,SL!B:C,2,0) -> Fint production line | G43: C | H43: =VLOOKUP(G43,'MvT types'!B:C,2,0) -> consumption | I43: -566.4 | J43: =VLOOKUP(B43,'list of materials'!A:E,5,0) -> 28 | K43: =I43*J43 -> -15859.2
A44: December | B44: 876145 | C44: =VLOOKUP(B44,'list of materials'!A:B,2,0) -> Fried Peanut | D44: =VLOOKUP(B44,'list of materials'!A:C,3,0) -> SFG | E44: Fint L | F44: =VLOOKUP(E44,SL!B:C,2,0) -> Fint production line | G44: C | H44: =VLOOKUP(G44,'MvT types'!B:C,2,0) -> consumption | I44: -164 | J44: =VLOOKUP(B44,'list of materials'!A:E,5,0) -> 28.75 | K44: =I44*J44 -> -4715
A45: December | B45: 765190 | C45: =VLOOKUP(B45,'list of materials'!A:B,2,0) -> Caramel | D45: =VLOOKUP(B45,'list of materials'!A:C,3,0) -> RM | E45: Fint L | F45: =VLOOKUP(E45,SL!B:C,2,0) -> Fint production line | G45: C | H45: =VLOOKUP(G45,'MvT types'!B:C,2,0) -> consumption | I45: -81.6 | J45: =VLOOKUP(B45,'list of materials'!A:E,5,0) -> 15 | K45: =I45*J45 -> -1224
A46: January | B46: 867156 | C46: =VLOOKUP(B46,'list of materials'!A:B,2,0) -> Chocolate mass | D46: =VLOOKUP(B46,'list of materials'!A:C,3,0) -> RM | E46: Fint L | F46: =VLOOKUP(E46,SL!B:C,2,0) -> Fint production line | G46: C | H46: =VLOOKUP(G46,'MvT types'!B:C,2,0) -> consumption | I46: -495.6 | J46: =VLOOKUP(B46,'list of materials'!A:F,6,0) -> 31 | K46: =I46*J46 -> -15363.6
A47: January | B47: 876145 | C47: =VLOOKUP(B47,'list of materials'!A:B,2,0) -> Fried Peanut | D47: =VLOOKUP(B47,'list of materials'!A:C,3,0) -> SFG | E47: Fint L | F47: =VLOOKUP(E47,SL!B:C,2,0) -> Fint production line | G47: C | H47: =VLOOKUP(G47,'MvT types'!B:C,2,0) -> consumption | I47: -143.5 | J47: =VLOOKUP(B47,'list of materials'!A:F,6,0) -> 27.6 | K47: =I47*J47 -> -3960.6
A48: January | B48: 765190 | C48: =VLOOKUP(B48,'list of materials'!A:B,2,0) -> Caramel | D48: =VLOOKUP(B48,'list of materials'!A:C,3,0) -> RM | E48: Fint L | F48: =VLOOKUP(E48,SL!B:C,2,0) -> Fint production line | G48: C | H48: =VLOOKUP(G48,'MvT types'!B:C,2,0) -> consumption | I48: -71.4 | J48: =VLOOKUP(B48,'list of materials'!A:F,6,0) -> 16 | K48: =I48*J48 -> -1142.4
A49: November | B49: 867156 | C49: =VLOOKUP(B49,'list of materials'!A:B,2,0) -> Chocolate mass | D49: =VLOOKUP(B49,'list of materials'!A:C,3,0) -> RM | E49: Fint L | F49: =VLOOKUP(E49,SL!B:C,2,0) -> Fint production line | G49: M | H49: =VLOOKUP(G49,'MvT types'!B:C,2,0) -> internal movement | I49: 361.08 | J49: =VLOOKUP(B49,'list of materials'!A:E,5,0) -> 28 | K49: =I49*J49 -> 10110.24
A50: November | B50: 876145 | C50: =VLOOKUP(B50,'list of materials'!A:B,2,0) -> Fried Peanut | D50: =VLOOKUP(B50,'list of materials'!A:C,3,0) -> SFG | E50: Fint L | F50: =VLOOKUP(E50,SL!B:C,2,0) -> Fint production line | G50: M | H50: =VLOOKUP(G50,'MvT types'!B:C,2,0) -> internal movement | I50: 104.55 | J50: =VLOOKUP(B50,'list of materials'!A:E,5,0) -> 28.75 | K50: =I50*J50 -> 3005.8125
A51: November | B51: 765190 | C51: =VLOOKUP(B51,'list of materials'!A:B,2,0) -> Caramel | D51: =VLOOKUP(B51,'list of materials'!A:C,3,0) -> RM | E51: Fint L | F51: =VLOOKUP(E51,SL!B:C,2,0) -> Fint production line | G51: M | H51: =VLOOKUP(G51,'MvT types'!B:C,2,0) -> internal movement | I51: 52.02 | J51: =VLOOKUP(B51,'list of materials'!A:E,5,0) -> 15 | K51: =I51*J51 -> 780.3
A52: December | B52: 867156 | C52: =VLOOKUP(B52,'list of materials'!A:B,2,0) -> Chocolate mass | D52: =VLOOKUP(B52,'list of materials'!A:C,3,0) -> RM | E52: Fint L | F52: =VLOOKUP(E52,SL!B:C,2,0) -> Fint production line | G52: M | H52: =VLOOKUP(G52,'MvT types'!B:C,2,0) -> internal movement | I52: 566.4 | J52: =VLOOKUP(B52,'list of materials'!A:E,5,0) -> 28 | K52: =I52*J52 -> 15859.2
A53: December | B53: 876145 | C53: =VLOOKUP(B53,'list of materials'!A:B,2,0) -> Fried Peanut | D53: =VLOOKUP(B53,'list of materials'!A:C,3,0) -> SFG | E53: Fint L | F53: =VLOOKUP(E53,SL!B:C,2,0) -> Fint production line | G53: M | H53: =VLOOKUP(G53,'MvT types'!B:C,2,0) -> internal movement | I53: 164 | J53: =VLOOKUP(B53,'list of materials'!A:E,5,0) -> 28.75 | K53: =I53*J53 -> 4715
A54: December | B54: 765190 | C54: =VLOOKUP(B54,'list of materials'!A:B,2,0) -> Caramel | D54: =VLOOKUP(B54,'list of materials'!A:C,3,0) -> RM | E54: Fint L | F54: =VLOOKUP(E54,SL!B:C,2,0) -> Fint production line | G54: M | H54: =VLOOKUP(G54,'MvT types'!B:C,2,0) -> internal movement | I54: 81.6 | J54: =VLOOKUP(B54,'list of materials'!A:E,5,0) -> 15 | K54: =I54*J54 -> 1224
A55: January | B55: 867156 | C55: =VLOOKUP(B55,'list of materials'!A:B,2,0) -> Chocolate mass | D55: =VLOOKUP(B55,'list of materials'!A:C,3,0) -> RM | E55: Fint L | F55: =VLOOKUP(E55,SL!B:C,2,0) -> Fint production line | G55: M | H55: =VLOOKUP(G55,'MvT types'!B:C,2,0) -> internal movement | I55: 495.6 | J55: =VLOOKUP(B55,'list of materials'!A:F,6,0) -> 31 | K55: =I55*J55 -> 15363.6
A56: January | B56: 876145 | C56: =VLOOKUP(B56,'list of materials'!A:B,2,0) -> Fried Peanut | D56: =VLOOKUP(B56,'list of materials'!A:C,3,0) -> SFG | E56: Fint L | F56: =VLOOKUP(E56,SL!B:C,2,0) -> Fint production line | G56: M | H56: =VLOOKUP(G56,'MvT types'!B:C,2,0) -> internal movement | I56: 143.5 | J56: =VLOOKUP(B56,'list of materials'!A:F,6,0) -> 27.6 | K56: =I56*J56 -> 3960.6
A57: January | B57: 765190 | C57: =VLOOKUP(B57,'list of materials'!A:B,2,0) -> Caramel | D57: =VLOOKUP(B57,'list of materials'!A:C,3,0) -> RM | E57: Fint L | F57: =VLOOKUP(E57,SL!B:C,2,0) -> Fint production line | G57: M | H57: =VLOOKUP(G57,'MvT types'!B:C,2,0) -> internal movement | I57: 71.4 | J57: =VLOOKUP(B57,'list of materials'!A:F,6,0) -> 16 | K57: =I57*J57 -> 1142.4
A58: November | B58: 867156 | C58: =VLOOKUP(B58,'list of materials'!A:B,2,0) -> Chocolate mass | D58: =VLOOKUP(B58,'list of materials'!A:C,3,0) -> RM | E58: IN | F58: =VLOOKUP(E58,SL!B:C,2,0) -> Inbound warehouse | G58: M | H58: =VLOOKUP(G58,'MvT types'!B:C,2,0) -> internal movement | I58: -361.08 | J58: =VLOOKUP(B58,'list of materials'!A:E,5,0) -> 28 | K58: =I58*J58 -> -10110.24
A59: November | B59: 876145 | C59: =VLOOKUP(B59,'list of materials'!A:B,2,0) -> Fried Peanut | D59: =VLOOKUP(B59,'list of materials'!A:C,3,0) -> SFG | E59: IN | F59: =VLOOKUP(E59,SL!B:C,2,0) -> Inbound warehouse | G59: M | H59: =VLOOKUP(G59,'MvT types'!B:C,2,0) -> internal movement | I59: -104.55 | J59: =VLOOKUP(B59,'list of materials'!A:E,5,0) -> 28.75 | K59: =I59*J59 -> -3005.8125
A60: November | B60: 765190 | C60: =VLOOKUP(B60,'list of materials'!A:B,2,0) -> Caramel | D60: =VLOOKUP(B60,'list of materials'!A:C,3,0) -> RM | E60: IN | F60: =VLOOKUP(E60,SL!B:C,2,0) -> Inbound warehouse | G60: M | H60: =VLOOKUP(G60,'MvT types'!B:C,2,0) -> internal movement | I60: -52.02 | J60: =VLOOKUP(B60,'list of materials'!A:E,5,0) -> 15 | K60: =I60*J60 -> -780.3
A61: December | B61: 867156 | C61: =VLOOKUP(B61,'list of materials'!A:B,2,0) -> Chocolate mass | D61: =VLOOKUP(B61,'list of materials'!A:C,3,0) -> RM | E61: IN | F61: =VLOOKUP(E61,SL!B:C,2,0) -> Inbound warehouse | G61: M | H61: =VLOOKUP(G61,'MvT types'!B:C,2,0) -> internal movement | I61: -566.4 | J61: =VLOOKUP(B61,'list of materials'!A:E,5,0) -> 28 | K61: =I61*J61 -> -15859.2
A62: December | B62: 876145 | C62: =VLOOKUP(B62,'list of materials'!A:B,2,0) -> Fried Peanut | D62: =VLOOKUP(B62,'list of materials'!A:C,3,0) -> SFG | E62: IN | F62: =VLOOKUP(E62,SL!B:C,2,0) -> Inbound warehouse | G62: M | H62: =VLOOKUP(G62,'MvT types'!B:C,2,0) -> internal movement | I62: -164 | J62: =VLOOKUP(B62,'list of materials'!A:E,5,0) -> 28.75 | K62: =I62*J62 -> -4715
A63: December | B63: 765190 | C63: =VLOOKUP(B63,'list of materials'!A:B,2,0) -> Caramel | D63: =VLOOKUP(B63,'list of materials'!A:C,3,0) -> RM | E63: IN | F63: =VLOOKUP(E63,SL!B:C,2,0) -> Inbound warehouse | G63: M | H63: =VLOOKUP(G63,'MvT types'!B:C,2,0) -> internal movement | I63: -81.6 | J63: =VLOOKUP(B63,'list of materials'!A:E,5,0) -> 15 | K63: =I63*J63 -> -1224
A64: January | B64: 867156 | C64: =VLOOKUP(B64,'list of materials'!A:B,2,0) -> Chocolate mass | D64: =VLOOKUP(B64,'list of materials'!A:C,3,0) -> RM | E64: IN | F64: =VLOOKUP(E64,SL!B:C,2,0) -> Inbound warehouse | G64: M | H64: =VLOOKUP(G64,'MvT types'!B:C,2,0) -> internal movement | I64: -495.6 | J64: =VLOOKUP(B64,'list of materials'!A:F,6,0) -> 31 | K64: =I64*J64 -> -15363.6
A65: January | B65: 876145 | C65: =VLOOKUP(B65,'list of materials'!A:B,2,0) -> Fried Peanut | D65: =VLOOKUP(B65,'list of materials'!A:C,3,0) -> SFG | E65: IN | F65: =VLOOKUP(E65,SL!B:C,2,0) -> Inbound warehouse | G65: M | H65: =VLOOKUP(G65,'MvT types'!B:C,2,0) -> internal movement | I65: -143.5 | J65: =VLOOKUP(B65,'list of materials'!A:F,6,0) -> 27.6 | K65: =I65*J65 -> -3960.6
A66: January | B66: 765190 | C66: =VLOOKUP(B66,'list of materials'!A:B,2,0) -> Caramel | D66: =VLOOKUP(B66,'list of materials'!A:C,3,0) -> RM | E66: IN | F66: =VLOOKUP(E66,SL!B:C,2,0) -> Inbound warehouse | G66: M | H66: =VLOOKUP(G66,'MvT types'!B:C,2,0) -> internal movement | I66: -71.4 | J66: =VLOOKUP(B66,'list of materials'!A:F,6,0) -> 16 | K66: =I66*J66 -> -1142.4
A67: November | B67: 657341 | C67: =VLOOKUP(B67,'list of materials'!A:B,2,0) -> Raw Peanut | D67: =VLOOKUP(B67,'list of materials'!A:C,3,0) -> RM | E67: IN | F67: =VLOOKUP(E67,SL!B:C,2,0) -> Inbound warehouse | G67: M | H67: =VLOOKUP(G67,'MvT types'!B:C,2,0) -> internal movement | I67: -120.6925 | J67: =VLOOKUP(B67,'list of materials'!A:E,5,0) -> 25 | K67: =I67*J67 -> -3017.3125
A68: December | B68: 657341 | C68: =VLOOKUP(B68,'list of materials'!A:B,2,0) -> Raw Peanut | D68: =VLOOKUP(B68,'list of materials'!A:C,3,0) -> RM | E68: IN | F68: =VLOOKUP(E68,SL!B:C,2,0) -> Inbound warehouse | G68: M | H68: =VLOOKUP(G68,'MvT types'!B:C,2,0) -> internal movement | I68: -235.8075 | J68: =VLOOKUP(B68,'list of materials'!A:E,5,0) -> 25 | K68: =I68*J68 -> -5895.1875
A69: January | B69: 657341 | C69: =VLOOKUP(B69,'list of materials'!A:B,2,0) -> Raw Peanut | D69: =VLOOKUP(B69,'list of materials'!A:C,3,0) -> RM | E69: IN | F69: =VLOOKUP(E69,SL!B:C,2,0) -> Inbound warehouse | G69: M | H69: =VLOOKUP(G69,'MvT types'!B:C,2,0) -> internal movement | I69: -115 | J69: =VLOOKUP(B69,'list of materials'!A:F,6,0) -> 24 | K69: =I69*J69 -> -2760
A70: November | B70: 657341 | C70: =VLOOKUP(B70,'list of materials'!A:B,2,0) -> Raw Peanut | D70: =VLOOKUP(B70,'list of materials'!A:C,3,0) -> RM | E70: NP | F70: =VLOOKUP(E70,SL!B:C,2,0) -> Nut plant | G70: M | H70: =VLOOKUP(G70,'MvT types'!B:C,2,0) -> internal movement | I70: 120.6925 | J70: =VLOOKUP(B70,'list of materials'!A:E,5,0) -> 25 | K70: =I70*J70 -> 3017.3125
A71: December | B71: 657341 | C71: =VLOOKUP(B71,'list of materials'!A:B,2,0) -> Raw Peanut | D71: =VLOOKUP(B71,'list of materials'!A:C,3,0) -> RM | E71: NP | F71: =VLOOKUP(E71,SL!B:C,2,0) -> Nut plant | G71: M | H71: =VLOOKUP(G71,'MvT types'!B:C,2,0) -> internal movement | I71: 235.8075 | J71: =VLOOKUP(B71,'list of materials'!A:E,5,0) -> 25 | K71: =I71*J71 -> 5895.1875
A72: January | B72: 657341 | C72: =VLOOKUP(B72,'list of materials'!A:B,2,0) -> Raw Peanut | D72: =VLOOKUP(B72,'list of materials'!A:C,3,0) -> RM | E72: NP | F72: =VLOOKUP(E72,SL!B:C,2,0) -> Nut plant | G72: M | H72: =VLOOKUP(G72,'MvT types'!B:C,2,0) -> internal movement | I72: 115 | J72: =VLOOKUP(B72,'list of materials'!A:F,6,0) -> 24 | K72: =I72*J72 -> 2760
A73: November | B73: 657341 | C73: =VLOOKUP(B73,'list of materials'!A:B,2,0) -> Raw Peanut | D73: =VLOOKUP(B73,'list of materials'!A:C,3,0) -> RM | E73: NP | F73: =VLOOKUP(E73,SL!B:C,2,0) -> Nut plant | G73: C | H73: =VLOOKUP(G73,'MvT types'!B:C,2,0) -> consumption | I73: -120.6925 | J73: =VLOOKUP(B73,'list of materials'!A:E,5,0) -> 25 | K73: =I73*J73 -> -3017.3125
A74: December | B74: 657341 | C74: =VLOOKUP(B74,'list of materials'!A:B,2,0) -> Raw Peanut | D74: =VLOOKUP(B74,'list of materials'!A:C,3,0) -> RM | E74: NP | F74: =VLOOKUP(E74,SL!B:C,2,0) -> Nut plant | G74: C | H74: =VLOOKUP(G74,'MvT types'!B:C,2,0) -> consumption | I74: -235.8075 | J74: =VLOOKUP(B74,'list of materials'!A:E,5,0) -> 25 | K74: =I74*J74 -> -5895.1875
A75: January | B75: 657341 | C75: =VLOOKUP(B75,'list of materials'!A:B,2,0) -> Raw Peanut | D75: =VLOOKUP(B75,'list of materials'!A:C,3,0) -> RM | E75: NP | F75: =VLOOKUP(E75,SL!B:C,2,0) -> Nut plant | G75: C | H75: =VLOOKUP(G75,'MvT types'!B:C,2,0) -> consumption | I75: -115 | J75: =VLOOKUP(B75,'list of materials'!A:F,6,0) -> 24 | K75: =I75*J75 -> -2760
A76: November | B76: 867156 | C76: =VLOOKUP(B76,'list of materials'!A:B,2,0) -> Chocolate mass | D76: =VLOOKUP(B76,'list of materials'!A:C,3,0) -> RM | E76: Step L | F76: =VLOOKUP(E76,SL!B:C,2,0) -> Step production line | G76: C | H76: =VLOOKUP(G76,'MvT types'!B:C,2,0) -> consumption | I76: -590 | J76: =VLOOKUP(B76,'list of materials'!A:E,5,0) -> 28 | K76: =I76*J76 -> -16520
A77: November | B77: 560196 | C77: =VLOOKUP(B77,'list of materials'!A:B,2,0) -> Biscuit | D77: =VLOOKUP(B77,'list of materials'!A:C,3,0) -> RM | E77: Step L | F77: =VLOOKUP(E77,SL!B:C,2,0) -> Step production line | G77: C | H77: =VLOOKUP(G77,'MvT types'!B:C,2,0) -> consumption | I77: -320 | J77: =VLOOKUP(B77,'list of materials'!A:E,5,0) -> 25 | K77: =I77*J77 -> -8000
A78: November | B78: 765190 | C78: =VLOOKUP(B78,'list of materials'!A:B,2,0) -> Caramel | D78: =VLOOKUP(B78,'list of materials'!A:C,3,0) -> RM | E78: Step L | F78: =VLOOKUP(E78,SL!B:C,2,0) -> Step production line | G78: C | H78: =VLOOKUP(G78,'MvT types'!B:C,2,0) -> consumption | I78: -95 | J78: =VLOOKUP(B78,'list of materials'!A:E,5,0) -> 15 | K78: =I78*J78 -> -1425
A79: December | B79: 867156 | C79: =VLOOKUP(B79,'list of materials'!A:B,2,0) -> Chocolate mass | D79: =VLOOKUP(B79,'list of materials'!A:C,3,0) -> RM | E79: Step L | F79: =VLOOKUP(E79,SL!B:C,2,0) -> Step production line | G79: C | H79: =VLOOKUP(G79,'MvT types'!B:C,2,0) -> consumption | I79: -885 | J79: =VLOOKUP(B79,'list of materials'!A:E,5,0) -> 28 | K79: =I79*J79 -> -24780
A80: December | B80: 560196 | C80: =VLOOKUP(B80,'list of materials'!A:B,2,0) -> Biscuit | D80: =VLOOKUP(B80,'list of materials'!A:C,3,0) -> RM | E80: Step L | F80: =VLOOKUP(E80,SL!B:C,2,0) -> Step production line | G80: C | H80: =VLOOKUP(G80,'MvT types'!B:C,2,0) -> consumption | I80: -480 | J80: =VLOOKUP(B80,'list of materials'!A:E,5,0) -> 25 | K80: =I80*J80 -> -12000
A81: December | B81: 765190 | C81: =VLOOKUP(B81,'list of materials'!A:B,2,0) -> Caramel | D81: =VLOOKUP(B81,'list of materials'!A:C,3,0) -> RM | E81: Step L | F81: =VLOOKUP(E81,SL!B:C,2,0) -> Step production line | G81: C | H81: =VLOOKUP(G81,'MvT types'!B:C,2,0) -> consumption | I81: -142.5 | J81: =VLOOKUP(B81,'list of materials'!A:E,5,0) -> 15 | K81: =I81*J81 -> -2137.5
A82: January | B82: 867156 | C82: =VLOOKUP(B82,'list of materials'!A:B,2,0) -> Chocolate mass | D82: =VLOOKUP(B82,'list of materials'!A:C,3,0) -> RM | E82: Step L | F82: =VLOOKUP(E82,SL!B:C,2,0) -> Step production line | G82: C | H82: =VLOOKUP(G82,'MvT types'!B:C,2,0) -> consumption | I82: -177 | J82: =VLOOKUP(B82,'list of materials'!A:F,6,0) -> 31 | K82: =I82*J82 -> -5487
A83: January | B83: 560196 | C83: =VLOOKUP(B83,'list of materials'!A:B,2,0) -> Biscuit | D83: =VLOOKUP(B83,'list of materials'!A:C,3,0) -> RM | E83: Step L | F83: =VLOOKUP(E83,SL!B:C,2,0) -> Step production line | G83: C | H83: =VLOOKUP(G83,'MvT types'!B:C,2,0) -> consumption | I83: -96 | J83: =VLOOKUP(B83,'list of materials'!A:F,6,0) -> 27 | K83: =I83*J83 -> -2592
A84: January | B84: 765190 | C84: =VLOOKUP(B84,'list of materials'!A:B,2,0) -> Caramel | D84: =VLOOKUP(B84,'list of materials'!A:C,3,0) -> RM | E84: Step L | F84: =VLOOKUP(E84,SL!B:C,2,0) -> Step production line | G84: C | H84: =VLOOKUP(G84,'MvT types'!B:C,2,0) -> consumption | I84: -28.5 | J84: =VLOOKUP(B84,'list of materials'!A:F,6,0) -> 16 | K84: =I84*J84 -> -456
A85: December | B85: 765190 | C85: =VLOOKUP(B85,'list of materials'!A:B,2,0) -> Caramel | D85: =VLOOKUP(B85,'list of materials'!A:C,3,0) -> RM | E85: IN | F85: =VLOOKUP(E85,SL!B:C,2,0) -> Inbound warehouse | G85: I | H85: =VLOOKUP(G85,'MvT types'!B:C,2,0) -> Inventory stock-take | I85: -20 | J85: =VLOOKUP(B85,'list of materials'!A:E,5,0) -> 15 | K85: =I85*J85 -> -300
A86: December | B86: 657341 | C86: =VLOOKUP(B86,'list of materials'!A:B,2,0) -> Raw Peanut | D86: =VLOOKUP(B86,'list of materials'!A:C,3,0) -> RM | E86: IN | F86: =VLOOKUP(E86,SL!B:C,2,0) -> Inbound warehouse | G86: I | H86: =VLOOKUP(G86,'MvT types'!B:C,2,0) -> Inventory stock-take | I86: -12 | J86: =VLOOKUP(B86,'list of materials'!A:E,5,0) -> 25 | K86: =I86*J86 -> -300
A87: November | B87: 657341 | C87: =VLOOKUP(B87,'list of materials'!A:B,2,0) -> Raw Peanut | D87: =VLOOKUP(B87,'list of materials'!A:C,3,0) -> RM | E87: NP | F87: =VLOOKUP(E87,SL!B:C,2,0) -> Nut plant | G87: W | H87: =VLOOKUP(G87,'MvT types'!B:C,2,0) -> Write-off | I87: -2 | J87: =VLOOKUP(B87,'list of materials'!A:E,5,0) -> 25 | K87: =I87*J87 -> -50
A88: December | B88: 657341 | C88: =VLOOKUP(B88,'list of materials'!A:B,2,0) -> Raw Peanut | D88: =VLOOKUP(B88,'list of materials'!A:C,3,0) -> RM | E88: NP | F88: =VLOOKUP(E88,SL!B:C,2,0) -> Nut plant | G88: W | H88: =VLOOKUP(G88,'MvT types'!B:C,2,0) -> Write-off | I88: -3 | J88: =VLOOKUP(B88,'list of materials'!A:E,5,0) -> 25 | K88: =I88*J88 -> -75
A89: January | B89: 657341 | C89: =VLOOKUP(B89,'list of materials'!A:B,2,0) -> Raw Peanut | D89: =VLOOKUP(B89,'list of materials'!A:C,3,0) -> RM | E89: NP | F89: =VLOOKUP(E89,SL!B:C,2,0) -> Nut plant | G89: W | H89: =VLOOKUP(G89,'MvT types'!B:C,2,0) -> Write-off | I89: -1 | J89: =VLOOKUP(B89,'list of materials'!A:F,6,0) -> 24 | K89: =I89*J89 -> -24
A90: November | B90: 867156 | C90: =VLOOKUP(B90,'list of materials'!A:B,2,0) -> Chocolate mass | D90: =VLOOKUP(B90,'list of materials'!A:C,3,0) -> RM | E90: Fint L | F90: =VLOOKUP(E90,SL!B:C,2,0) -> Fint production line | G90: W | H90: =VLOOKUP(G90,'MvT types'!B:C,2,0) -> Write-off | I90: 4.08 | J90: =VLOOKUP(B90,'list of materials'!A:E,5,0) -> 28 | K90: =I90*J90 -> 114.24
A91: December | B91: 867156 | C91: =VLOOKUP(B91,'list of materials'!A:B,2,0) -> Chocolate mass | D91: =VLOOKUP(B91,'list of materials'!A:C,3,0) -> RM | E91: Fint L | F91: =VLOOKUP(E91,SL!B:C,2,0) -> Fint production line | G91: W | H91: =VLOOKUP(G91,'MvT types'!B:C,2,0) -> Write-off | I91: -2 | J91: =VLOOKUP(B91,'list of materials'!A:E,5,0) -> 28 | K91: =I91*J91 -> -56
A92: January | B92: 867156 | C92: =VLOOKUP(B92,'list of materials'!A:B,2,0) -> Chocolate mass | D92: =VLOOKUP(B92,'list of materials'!A:C,3,0) -> RM | E92: Fint L | F92: =VLOOKUP(E92,SL!B:C,2,0) -> Fint production line | G92: W | H92: =VLOOKUP(G92,'MvT types'!B:C,2,0) -> Write-off | I92: -4 | J92: =VLOOKUP(B92,'list of materials'!A:F,6,0) -> 31 | K92: =I92*J92 -> -124
A93: November | B93: 765190 | C93: =VLOOKUP(B93,'list of materials'!A:B,2,0) -> Caramel | D93: =VLOOKUP(B93,'list of materials'!A:C,3,0) -> RM | E93: Fint L | F93: =VLOOKUP(E93,SL!B:C,2,0) -> Fint production line | G93: W | H93: =VLOOKUP(G93,'MvT types'!B:C,2,0) -> Write-off | I93: -3.98 | J93: =VLOOKUP(B93,'list of materials'!A:E,5,0) -> 15 | K93: =I93*J93 -> -59.7
A94: December | B94: 765190 | C94: =VLOOKUP(B94,'list of materials'!A:B,2,0) -> Caramel | D94: =VLOOKUP(B94,'list of materials'!A:C,3,0) -> RM | E94: Fint L | F94: =VLOOKUP(E94,SL!B:C,2,0) -> Fint production line | G94: W | H94: =VLOOKUP(G94,'MvT types'!B:C,2,0) -> Write-off | I94: -1 | J94: =VLOOKUP(B94,'list of materials'!A:E,5,0) -> 15 | K94: =I94*J94 -> -15
A95: January | B95: 765190 | C95: =VLOOKUP(B95,'list of materials'!A:B,2,0) -> Caramel | D95: =VLOOKUP(B95,'list of materials'!A:C,3,0) -> RM | E95: Fint L | F95: =VLOOKUP(E95,SL!B:C,2,0) -> Fint production line | G95: W | H95: =VLOOKUP(G95,'MvT types'!B:C,2,0) -> Write-off | I95: -2 | J95: =VLOOKUP(B95,'list of materials'!A:F,6,0) -> 16 | K95: =I95*J95 -> -32
A96: November | B96: 867156 | C96: =VLOOKUP(B96,'list of materials'!A:B,2,0) -> Chocolate mass | D96: =VLOOKUP(B96,'list of materials'!A:C,3,0) -> RM | E96: Step L | F96: =VLOOKUP(E96,SL!B:C,2,0) -> Step production line | G96: W | H96: =VLOOKUP(G96,'MvT types'!B:C,2,0) -> Write-off | I96: -1 | J96: =VLOOKUP(B96,'list of materials'!A:E,5,0) -> 28 | K96: =I96*J96 -> -28
A97: December | B97: 867156 | C97: =VLOOKUP(B97,'list of materials'!A:B,2,0) -> Chocolate mass | D97: =VLOOKUP(B97,'list of materials'!A:C,3,0) -> RM | E97: Step L | F97: =VLOOKUP(E97,SL!B:C,2,0) -> Step production line | G97: W | H97: =VLOOKUP(G97,'MvT types'!B:C,2,0) -> Write-off | I97: -1 | J97: =VLOOKUP(B97,'list of materials'!A:E,5,0) -> 28 | K97: =I97*J97 -> -28
A98: January | B98: 867156 | C98: =VLOOKUP(B98,'list of materials'!A:B,2,0) -> Chocolate mass | D98: =VLOOKUP(B98,'list of materials'!A:C,3,0) -> RM | E98: Step L | F98: =VLOOKUP(E98,SL!B:C,2,0) -> Step production line | G98: W | H98: =VLOOKUP(G98,'MvT types'!B:C,2,0) -> Write-off | I98: -2 | J98: =VLOOKUP(B98,'list of materials'!A:F,6,0) -> 31 | K98: =I98*J98 -> -62
A99: November | B99: 560196 | C99: =VLOOKUP(B99,'list of materials'!A:B,2,0) -> Biscuit | D99: =VLOOKUP(B99,'list of materials'!A:C,3,0) -> RM | E99: Step L | F99: =VLOOKUP(E99,SL!B:C,2,0) -> Step production line | G99: W | H99: =VLOOKUP(G99,'MvT types'!B:C,2,0) -> Write-off | I99: -20 | J99: =VLOOKUP(B99,'list of materials'!A:E,5,0) -> 25 | K99: =I99*J99 -> -500
A100: December | B100: 560196 | C100: =VLOOKUP(B100,'list of materials'!A:B,2,0) -> Biscuit | D100: =VLOOKUP(B100,'list of materials'!A:C,3,0) -> RM | E100: Step L | F100: =VLOOKUP(E100,SL!B:C,2,0) -> Step production line | G100: W | H100: =VLOOKUP(G100,'MvT types'!B:C,2,0) -> Write-off | I100: -1 | J100: =VLOOKUP(B100,'list of materials'!A:E,5,0) -> 25 | K100: =I100*J100 -> -25
...

Sheet MvT pivot
A1: Sum of Amount local currency | D1: Month
A2: Storage location | B2: Movement type | C2: Mat descr | D2: October | E2: November | F2: December | G2: January
A3: Fint production line | B3: consumption | C3: Caramel | E3: -780.3 | F3: -1224 | G3: -1142.4
C4: Chocolate mass | E4: -10110.24 | F4: -15859.2 | G4: -15363.6
C5: Fried Peanut | E5: -3005.8125 | F5: -4715 | G5: -3960.6
B6: consumption Total | E6: -13896.352 | F6: -21798.2 | G6: -20466.6
B7: internal movement | C7: Caramel | E7: 780.3 | F7: 1224 | G7: 1142.4
C8: Chocolate mass | E8: 10110.24 | F8: 15859.2 | G8: 15363.6
C9: Fried Peanut | E9: 6168.3125 | F9: 10610.188 | G9: 6720.6
B10: internal movement Total | E10: 17058.853 | F10: 27693.388 | G10: 23226.6
B11: Write-off | C11: Caramel | E11: -59.7 | F11: -15 | G11: -32
C12: Chocolate mass | E12: 114.24 | F12: -56 | G12: -124
B13: Write-off Total | E13: 54.54 | F13: -71 | G13: -156
A14: Fint production line Total | E14: 3217.04 | F14: 5824.1875 | G14: 2604
A15: Inbound warehouse | B15: internal movement | C15: Caramel | E15: -780.3 | F15: -1224 | G15: -1142.4
C16: Chocolate mass | E16: -10110.24 | F16: -15859.2 | G16: -15363.6
C17: Fried Peanut | E17: -3005.8125 | F17: -4715 | G17: -3960.6
C18: Raw Peanut | E18: -3017.3125 | F18: -5895.1875 | G18: -2760
B19: internal movement Total | E19: -16913.665 | F19: -27693.388 | G19: -23226.6
B20: Inventory stock-take | C20: Caramel | F20: -300
C21: Fint | F21: -272.4775
C22: Fried Peanut | F22: -86.25
C23: Raw Peanut | F23: -300
B24: Inventory stock-take Total | F24: -958.7275
B25: reception | C25: Biscuit | D25: 5750 | E25: 12500 | F25: 2500 | G25: 2403
C26: Caramel | D26: 2970 | E26: 3000 | F26: 750 | G26: 800
C27: Chocolate mass | D27: 69468 | E27: 11200 | F27: 2800 | G27: 3100
C28: Raw Peanut | D28: 2237.5 | E28: 7500 | F28: 1250 | G28: 1200
B29: reception Total | D29: 80425.5 | E29: 34200 | F29: 7300 | G29: 7503
A30: Inbound warehouse Total | D30: 80425.5 | E30: 17286.335 | F30: -21352.115 | G30: -15723.6
A31: Nut plant | B31: consumption | C31: Raw Peanut | E31: -3017.3125 | F31: -5895.1875 | G31: -2760
B32: consumption Total | E32: -3017.3125 | F32: -5895.1875 | G32: -2760
B33: goods production | C33: Fried Peanut | E33: 3162.5 | F33: 5895.1875 | G33: 2760
B34: goods production Total | E34: 3162.5 | F34: 5895.1875 | G34: 2760
B35: internal movement | C35: Fried Peanut | E35: -3162.5 | F35: -5895.1875 | G35: -2760
C36: Raw Peanut | E36: 3017.3125 | F36: 5895.1875 | G36: 2760
B37: internal movement Total | E37: -145.1875 | F37: 0 | G37: 0
B38: Write-off | C38: Raw Peanut | E38: -50 | F38: -75 | G38: -24
B39: Write-off Total | E39: -50 | F39: -75 | G39: -24
A40: Nut plant Total | E40: -50 | F40: -75 | G40: -24
A41: Outbound warehouse | B41: dispatch | C41: Fint | E41: -8174.325 | F41: -24522.975 | G41: -23407.84
C42: Step | E42: -12972.5 | F42: -33728.5 | G42: -28450
B43: dispatch Total | E43: -21146.825 | F43: -58251.475 | G43: -51857.84
B44: internal movement | C44: Fint | E44: 13896.352 | F44: 21798.2 | G44: 20481.86
C45: Step | E45: 25945 | F45: 38917.5 | G45: 8620.35
B46: internal movement Total | E46: 39841.353 | F46: 60715.7 | G46: 29102.21
B47: Write-off | C47: Step | G47: -85.35
B48: Write-off Total | G48: -85.35
A49: Outbound warehouse Total | E49: 18694.527 | F49: 2464.225 | G49: -22840.98
A50: Palletizer | B50: goods production | C50: Fint | E50: 13896.352 | F50: 21798.2 | G50: 20481.86
C51: Step | E51: 25945 | F51: 38917.5 | G51: 8620.35
B52: goods production Total | E52: 39841.353 | F52: 60715.7 | G52: 29102.21
B53: internal movement | C53: Fint | E53: -13896.352 | F53: -21798.2 | G53: -20481.86
C54: Step | E54: -25945 | F54: -38917.5 | G54: -8620.35
B55: internal movement Total | E55: -39841.353 | F55: -60715.7 | G55: -29102.21
A56: Palletizer Total | E56: 0 | F56: 0 | G56: -1.8189894e-12
A57: Step production line | B57: consumption | C57: Biscuit | E57: -8000 | F57: -12000 | G57: -2592
C58: Caramel | E58: -1425 | F58: -2137.5 | G58: -456
C59: Chocolate mass | E59: -16520 | F59: -24780 | G59: -5487
B60: consumption Total | E60: -25945 | F60: -38917.5 | G60: -8535
B61: Write-off | C61: Biscuit | E61: -500 | F61: -25 | G61: -54
C62: Chocolate mass | E62: -28 | F62: -28 | G62: -62
B63: Write-off Total | E63: -528 | F63: -53 | G63: -116
A64: Step production line Total | E64: -26473 | F64: -38970.5 | G64: -8651
A65: Grand Total | D65: 80425.5 | E65: 12674.903 | F65: -52109.202 | G65: -44635.58

Sheet Stocks
C1: Mat number | D1: Material | E1: October | F1: November | G1: December | H1: January
B2: Opening stock | C2: 120301 | D2: Fint | E2: 0 | F2: =E23 -> 0 | G2: =F23 -> 210 | H2: =G23 -> 100 | J2: R | K2: =VLOOKUP(J2,'MvT types'!B:C,2,0) -> reception
C3: 156212 | D3: Step | E3: 0 | F3: =E24 -> 0 | G3: =F24 -> 500 | H3: =G24 -> 700 | J3: C | K3: =VLOOKUP(J3,'MvT types'!B:C,2,0) -> consumption
C4: 867156 | D4: Chocolate mass | E4: 0 | F4: =E25 -> 2481 | G4: =F25 -> 1933 | H4: =G25 -> 578.6 | J4: M | K4: =VLOOKUP(J4,'MvT types'!B:C,2,0) -> internal movement
C5: 765190 | D5: Caramel | E5: 0 | F5: =E26 -> 198 | G5: =F26 -> 247 | H5: =G26 -> 51.9 | J5: P | K5: =VLOOKUP(J5,'MvT types'!B:C,2,0) -> goods production
C6: 657341 | D6: Raw Peanut | E6: 0 | F6: =E27 -> 89.5 | G6: =F27 -> 266.8075 | H6: =G27 -> 66 | J6: W | K6: =VLOOKUP(J6,'MvT types'!B:C,2,0) -> Write-off
C7: 876145 | D7: Fried Peanut | E7: 0 | F7: =E28 -> 0 | G7: =F28 -> 5.45 | H7: =G28 -> 43.5 | J7: I | K7: =VLOOKUP(J7,'MvT types'!B:C,2,0) -> Inventory stock-take
C8: 560196 | D8: Biscuit | E8: 0 | F8: =E29 -> 230 | G8: =F29 -> 390 | H8: =G29 -> 9 | J8: D | K8: =VLOOKUP(J8,'MvT types'!B:C,2,0) -> dispatch
B9: Inflow | C9: 120301 | D9: Fint | E9: =SUMIFS(Movements!$I:$I,Movements!$G:$G,$J$2,Movements!$B:$B,$C9,Movements!$A:$A,Stocks!E$1)+SUMIFS(Movements!$I:$I,Movements!$G:$G,$J$5,Movements!$B:$B,$C9,Movements!$A:$A,Stocks!E$1) -> 0 | F9: =SUMIFS(Movements!$I:$I,Movements!$G:$G,$J$2,Movements!$B:$B,$C9,Movements!$A:$A,Stocks!F$1)+SUMIFS(Movements!$I:$I,Movements!$G:$G,$J$5,Movements!$B:$B,$C9,Movements!$A:$A,Stocks!F$1) -> 510 | G9: =SUMIFS(Movements!$I:$I,Movements!$G:$G,$J$2,Movements!$B:$B,$C9,Movements!$A:$A,Stocks!G$1)+SUMIFS(Movements!$I:$I,Movements!$G:$G,$J$5,Movements!$B:$B,$C9,Movements!$A:$A,Stocks!G$1) -> 800 | H9: =SUMIFS(Movements!$I:$I,Movements!$G:$G,$J$2,Movements!$B:$B,$C9,Movements!$A:$A,Stocks!H$1)+SUMIFS(Movements!$I:$I,Movements!$G:$G,$J$5,Movements!$B:$B,$C9,Movements!$A:$A,Stocks!H$1) -> 700
C10: 156212 | D10: Step | E10: =SUMIFS(Movements!$I:$I,Movements!$G:$G,$J$2,Movements!$B:$B,$C10,Movements!$A:$A,Stocks!E$1)+SUMIFS(Movements!$I:$I,Movements!$G:$G,$J$5,Movements!$B:$B,$C10,Movements!$A:$A,Stocks!E$1) -> 0 | F10: =SUMIFS(Movements!$I:$I,Movements!$G:$G,$J$2,Movements!$B:$B,$C10,Movements!$A:$A,Stocks!F$1)+SUMIFS(Movements!$I:$I,Movements!$G:$G,$J$5,Movements!$B:$B,$C10,Movements!$A:$A,Stocks!F$1) -> 1000 | G10: =SUMIFS(Movements!$I:$I,Movements!$G:$G,$J$2,Movements!$B:$B,$C10,Movements!$A:$A,Stocks!G$1)+SUMIFS(Movements!$I:$I,Movements!$G:$G,$J$5,Movements!$B:$B,$C10,Movements!$A:$A,Stocks!G$1) -> 1500 | H10: =SUMIFS(Movements!$I:$I,Movements!$G:$G,$J$2,Movements!$B:$B,$C10,Movements!$A:$A,Stocks!H$1)+SUMIFS(Movements!$I:$I,Movements!$G:$G,$J$5,Movements!$B:$B,$C10,Movements!$A:$A,Stocks!H$1) -> 303
C11: 867156 | D11: Chocolate mass | E11: =SUMIFS(Movements!$I:$I,Movements!$G:$G,$J$2,Movements!$B:$B,$C11,Movements!$A:$A,Stocks!E$1)+SUMIFS(Movements!$I:$I,Movements!$G:$G,$J$5,Movements!$B:$B,$C11,Movements!$A:$A,Stocks!E$1) -> 2481 | F11: =SUMIFS(Movements!$I:$I,Movements!$G:$G,$J$2,Movements!$B:$B,$C11,Movements!$A:$A,Stocks!F$1)+SUMIFS(Movements!$I:$I,Movements!$G:$G,$J$5,Movements!$B:$B,$C11,Movements!$A:$A,Stocks!F$1) -> 400 | G11: =SUMIFS(Movements!$I:$I,Movements!$G:$G,$J$2,Movements!$B:$B,$C11,Movements!$A:$A,Stocks!G$1)+SUMIFS(Movements!$I:$I,Movements!$G:$G,$J$5,Movements!$B:$B,$C11,Movements!$A:$A,Stocks!G$1) -> 100 | H11: =SUMIFS(Movements!$I:$I,Movements!$G:$G,$J$2,Movements!$B:$B,$C11,Movements!$A:$A,Stocks!H$1)+SUMIFS(Movements!$I:$I,Movements!$G:$G,$J$5,Movements!$B:$B,$C11,Movements!$A:$A,Stocks!H$1) -> 100
C12: 765190 | D12: Caramel | E12: =SUMIFS(Movements!$I:$I,Movements!$G:$G,$J$2,Movements!$B:$B,$C12,Movements!$A:$A,Stocks!E$1)+SUMIFS(Movements!$I:$I,Movements!$G:$G,$J$5,Movements!$B:$B,$C12,Movements!$A:$A,Stocks!E$1) -> 198 | F12: =SUMIFS(Movements!$I:$I,Movements!$G:$G,$J$2,Movements!$B:$B,$C12,Movements!$A:$A,Stocks!F$1)+SUMIFS(Movements!$I:$I,Movements!$G:$G,$J$5,Movements!$B:$B,$C12,Movements!$A:$A,Stocks!F$1) -> 200 | G12: =SUMIFS(Movements!$I:$I,Movements!$G:$G,$J$2,Movements!$B:$B,$C12,Movements!$A:$A,Stocks!G$1)+SUMIFS(Movements!$I:$I,Movements!$G:$G,$J$5,Movements!$B:$B,$C12,Movements!$A:$A,Stocks!G$1) -> 50 | H12: =SUMIFS(Movements!$I:$I,Movements!$G:$G,$J$2,Movements!$B:$B,$C12,Movements!$A:$A,Stocks!H$1)+SUMIFS(Movements!$I:$I,Movements!$G:$G,$J$5,Movements!$B:$B,$C12,Movements!$A:$A,Stocks!H$1) -> 50
C13: 657341 | D13: Raw Peanut | E13: =SUMIFS(Movements!$I:$I,Movements!$G:$G,$J$2,Movements!$B:$B,$C13,Movements!$A:$A,Stocks!E$1)+SUMIFS(Movements!$I:$I,Movements!$G:$G,$J$5,Movements!$B:$B,$C13,Movements!$A:$A,Stocks!E$1) -> 89.5 | F13: =SUMIFS(Movements!$I:$I,Movements!$G:$G,$J$2,Movements!$B:$B,$C13,Movements!$A:$A,Stocks!F$1)+SUMIFS(Movements!$I:$I,Movements!$G:$G,$J$5,Movements!$B:$B,$C13,Movements!$A:$A,Stocks!F$1) -> 300 | G13: =SUMIFS(Movements!$I:$I,Movements!$G:$G,$J$2,Movements!$B:$B,$C13,Movements!$A:$A,Stocks!G$1)+SUMIFS(Movements!$I:$I,Movements!$G:$G,$J$5,Movements!$B:$B,$C13,Movements!$A:$A,Stocks!G$1) -> 50 | H13: =SUMIFS(Movements!$I:$I,Movements!$G:$G,$J$2,Movements!$B:$B,$C13,Movements!$A:$A,Stocks!H$1)+SUMIFS(Movements!$I:$I,Movements!$G:$G,$J$5,Movements!$B:$B,$C13,Movements!$A:$A,Stocks!H$1) -> 50
C14: 876145 | D14: Fried Peanut | E14: =SUMIFS(Movements!$I:$I,Movements!$G:$G,$J$2,Movements!$B:$B,$C14,Movements!$A:$A,Stocks!E$1)+SUMIFS(Movements!$I:$I,Movements!$G:$G,$J$5,Movements!$B:$B,$C14,Movements!$A:$A,Stocks!E$1) -> 0 | F14: =SUMIFS(Movements!$I:$I,Movements!$G:$G,$J$2,Movements!$B:$B,$C14,Movements!$A:$A,Stocks!F$1)+SUMIFS(Movements!$I:$I,Movements!$G:$G,$J$5,Movements!$B:$B,$C14,Movements!$A:$A,Stocks!F$1) -> 110 | G14: =SUMIFS(Movements!$I:$I,Movements!$G:$G,$J$2,Movements!$B:$B,$C14,Movements!$A:$A,Stocks!G$1)+SUMIFS(Movements!$I:$I,Movements!$G:$G,$J$5,Movements!$B:$B,$C14,Movements!$A:$A,Stocks!G$1) -> 205.05 | H14: =SUMIFS(Movements!$I:$I,Movements!$G:$G,$J$2,Movements!$B:$B,$C14,Movements!$A:$A,Stocks!H$1)+SUMIFS(Movements!$I:$I,Movements!$G:$G,$J$5,Movements!$B:$B,$C14,Movements!$A:$A,Stocks!H$1) -> 100
C15: 560196 | D15: Biscuit | E15: =SUMIFS(Movements!$I:$I,Movements!$G:$G,$J$2,Movements!$B:$B,$C15,Movements!$A:$A,Stocks!E$1)+SUMIFS(Movements!$I:$I,Movements!$G:$G,$J$5,Movements!$B:$B,$C15,Movements!$A:$A,Stocks!E$1) -> 230 | F15: =SUMIFS(Movements!$I:$I,Movements!$G:$G,$J$2,Movements!$B:$B,$C15,Movements!$A:$A,Stocks!F$1)+SUMIFS(Movements!$I:$I,Movements!$G:$G,$J$5,Movements!$B:$B,$C15,Movements!$A:$A,Stocks!F$1) -> 500 | G15: =SUMIFS(Movements!$I:$I,Movements!$G:$G,$J$2,Movements!$B:$B,$C15,Movements!$A:$A,Stocks!G$1)+SUMIFS(Movements!$I:$I,Movements!$G:$G,$J$5,Movements!$B:$B,$C15,Movements!$A:$A,Stocks!G$1) -> 100 | H15: =SUMIFS(Movements!$I:$I,Movements!$G:$G,$J$2,Movements!$B:$B,$C15,Movements!$A:$A,Stocks!H$1)+SUMIFS(Movements!$I:$I,Movements!$G:$G,$J$5,Movements!$B:$B,$C15,Movements!$A:$A,Stocks!H$1) -> 89
B16: Outflow | C16: 120301 | D16: Fint | E16: =SUMIFS(Movements!$I:$I,Movements!$G:$G,$J$3,Movements!$B:$B,$C16,Movements!$A:$A,Stocks!E$1)+SUMIFS(Movements!$I:$I,Movements!$G:$G,$J$6,Movements!$B:$B,$C16,Movements!$A:$A,Stocks!E$1)+SUMIFS(Movements!$I:$I,Movements!$G:$G,$J$7,Movements!$B:$B,$C16,Movements!$A:$A,Stocks!E$1)+SUMIFS(Movements!$I:$I,Movements!$G:$G,$J$8,Movements!$B:$B,$C16,Movements!$A:$A,Stocks!E$1) -> 0 | F16: =SUMIFS(Movements!$I:$I,Movements!$G:$G,$J$3,Movements!$B:$B,$C16,Movements!$A:$A,Stocks!F$1)+SUMIFS(Movements!$I:$I,Movements!$G:$G,$J$6,Movements!$B:$B,$C16,Movements!$A:$A,Stocks!F$1)+SUMIFS(Movements!$I:$I,Movements!$G:$G,$J$7,Movements!$B:$B,$C16,Movements!$A:$A,Stocks!F$1)+SUMIFS(Movements!$I:$I,Movements!$G:$G,$J$8,Movements!$B:$B,$C16,Movements!$A:$A,Stocks!F$1) -> -300 | G16: =SUMIFS(Movements!$I:$I,Movements!$G:$G,$J$3,Movements!$B:$B,$C16,Movements!$A:$A,Stocks!G$1)+SUMIFS(Movements!$I:$I,Movements!$G:$G,$J$6,Movements!$B:$B,$C16,Movements!$A:$A,Stocks!G$1)+SUMIFS(Movements!$I:$I,Movements!$G:$G,$J$7,Movements!$B:$B,$C16,Movements!$A:$A,Stocks!G$1)+SUMIFS(Movements!$I:$I,Movements!$G:$G,$J$8,Movements!$B:$B,$C16,Movements!$A:$A,Stocks!G$1) -> -910 | H16: =SUMIFS(Movements!$I:$I,Movements!$G:$G,$J$3,Movements!$B:$B,$C16,Movements!$A:$A,Stocks!H$1)+SUMIFS(Movements!$I:$I,Movements!$G:$G,$J$6,Movements!$B:$B,$C16,Movements!$A:$A,Stocks!H$1)+SUMIFS(Movements!$I:$I,Movements!$G:$G,$J$7,Movements!$B:$B,$C16,Movements!$A:$A,Stocks!H$1)+SUMIFS(Movements!$I:$I,Movements!$G:$G,$J$8,Movements!$B:$B,$C16,Movements!$A:$A,Stocks!H$1) -> -800
C17: 156212 | D17: Step | E17: =SUMIFS(Movements!$I:$I,Movements!$G:$G,$J$3,Movements!$B:$B,$C17,Movements!$A:$A,Stocks!E$1)+SUMIFS(Movements!$I:$I,Movements!$G:$G,$J$6,Movements!$B:$B,$C17,Movements!$A:$A,Stocks!E$1)+SUMIFS(Movements!$I:$I,Movements!$G:$G,$J$7,Movements!$B:$B,$C17,Movements!$A:$A,Stocks!E$1)+SUMIFS(Movements!$I:$I,Movements!$G:$G,$J$8,Movements!$B:$B,$C17,Movements!$A:$A,Stocks!E$1) -> 0 | F17: =SUMIFS(Movements!$I:$I,Movements!$G:$G,$J$3,Movements!$B:$B,$C17,Movements!$A:$A,Stocks!F$1)+SUMIFS(Movements!$I:$I,Movements!$G:$G,$J$6,Movements!$B:$B,$C17,Movements!$A:$A,Stocks!F$1)+SUMIFS(Movements!$I:$I,Movements!$G:$G,$J$7,Movements!$B:$B,$C17,Movements!$A:$A,Stocks!F$1)+SUMIFS(Movements!$I:$I,Movements!$G:$G,$J$8,Movements!$B:$B,$C17,Movements!$A:$A,Stocks!F$1) -> -500 | G17: =SUMIFS(Movements!$I:$I,Movements!$G:$G,$J$3,Movements!$B:$B,$C17,Movements!$A:$A,Stocks!G$1)+SUMIFS(Movements!$I:$I,Movements!$G:$G,$J$6,Movements!$B:$B,$C17,Movements!$A:$A,Stocks!G$1)+SUMIFS(Movements!$I:$I,Movements!$G:$G,$J$7,Movements!$B:$B,$C17,Movements!$A:$A,Stocks!G$1)+SUMIFS(Movements!$I:$I,Movements!$G:$G,$J$8,Movements!$B:$B,$C17,Movements!$A:$A,Stocks!G$1) -> -1300 | H17: =SUMIFS(Movements!$I:$I,Movements!$G:$G,$J$3,Movements!$B:$B,$C17,Movements!$A:$A,Stocks!H$1)+SUMIFS(Movements!$I:$I,Movements!$G:$G,$J$6,Movements!$B:$B,$C17,Movements!$A:$A,Stocks!H$1)+SUMIFS(Movements!$I:$I,Movements!$G:$G,$J$7,Movements!$B:$B,$C17,Movements!$A:$A,Stocks!H$1)+SUMIFS(Movements!$I:$I,Movements!$G:$G,$J$8,Movements!$B:$B,$C17,Movements!$A:$A,Stocks!H$1) -> -1003
C18: 867156 | D18: Chocolate mass | E18: =SUMIFS(Movements!$I:$I,Movements!$G:$G,$J$3,Movements!$B:$B,$C18,Movements!$A:$A,Stocks!E$1)+SUMIFS(Movements!$I:$I,Movements!$G:$G,$J$6,Movements!$B:$B,$C18,Movements!$A:$A,Stocks!E$1)+SUMIFS(Movements!$I:$I,Movements!$G:$G,$J$7,Movements!$B:$B,$C18,Movements!$A:$A,Stocks!E$1)+SUMIFS(Movements!$I:$I,Movements!$G:$G,$J$8,Movements!$B:$B,$C18,Movements!$A:$A,Stocks!E$1) -> 0 | F18: =SUMIFS(Movements!$I:$I,Movements!$G:$G,$J$3,Movements!$B:$B,$C18,Movements!$A:$A,Stocks!F$1)+SUMIFS(Movements!$I:$I,Movements!$G:$G,$J$6,Movements!$B:$B,$C18,Movements!$A:$A,Stocks!F$1)+SUMIFS(Movements!$I:$I,Movements!$G:$G,$J$7,Movements!$B:$B,$C18,Movements!$A:$A,Stocks!F$1)+SUMIFS(Movements!$I:$I,Movements!$G:$G,$J$8,Movements!$B:$B,$C18,Movements!$A:$A,Stocks!F$1) -> -948 | G18: =SUMIFS(Movements!$I:$I,Movements!$G:$G,$J$3,Movements!$B:$B,$C18,Movements!$A:$A,Stocks!G$1)+SUMIFS(Movements!$I:$I,Movements!$G:$G,$J$6,Movements!$B:$B,$C18,Movements!$A:$A,Stocks!G$1)+SUMIFS(Movements!$I:$I,Movements!$G:$G,$J$7,Movements!$B:$B,$C18,Movements!$A:$A,Stocks!G$1)+SUMIFS(Movements!$I:$I,Movements!$G:$G,$J$8,Movements!$B:$B,$C18,Movements!$A:$A,Stocks!G$1) -> -1454.4 | H18: =SUMIFS(Movements!$I:$I,Movements!$G:$G,$J$3,Movements!$B:$B,$C18,Movements!$A:$A,Stocks!H$1)+SUMIFS(Movements!$I:$I,Movements!$G:$G,$J$6,Movements!$B:$B,$C18,Movements!$A:$A,Stocks!H$1)+SUMIFS(Movements!$I:$I,Movements!$G:$G,$J$7,Movements!$B:$B,$C18,Movements!$A:$A,Stocks!H$1)+SUMIFS(Movements!$I:$I,Movements!$G:$G,$J$8,Movements!$B:$B,$C18,Movements!$A:$A,Stocks!H$1) -> -678.6
C19: 765190 | D19: Caramel | E19: =SUMIFS(Movements!$I:$I,Movements!$G:$G,$J$3,Movements!$B:$B,$C19,Movements!$A:$A,Stocks!E$1)+SUMIFS(Movements!$I:$I,Movements!$G:$G,$J$6,Movements!$B:$B,$C19,Movements!$A:$A,Stocks!E$1)+SUMIFS(Movements!$I:$I,Movements!$G:$G,$J$7,Movements!$B:$B,$C19,Movements!$A:$A,Stocks!E$1)+SUMIFS(Movements!$I:$I,Movements!$G:$G,$J$8,Movements!$B:$B,$C19,Movements!$A:$A,Stocks!E$1) -> 0 | F19: =SUMIFS(Movements!$I:$I,Movements!$G:$G,$J$3,Movements!$B:$B,$C19,Movements!$A:$A,Stocks!F$1)+SUMIFS(Movements!$I:$I,Movements!$G:$G,$J$6,Movements!$B:$B,$C19,Movements!$A:$A,Stocks!F$1)+SUMIFS(Movements!$I:$I,Movements!$G:$G,$J$7,Movements!$B:$B,$C19,Movements!$A:$A,Stocks!F$1)+SUMIFS(Movements!$I:$I,Movements!$G:$G,$J$8,Movements!$B:$B,$C19,Movements!$A:$A,Stocks!F$1) -> -151 | G19: =SUMIFS(Movements!$I:$I,Movements!$G:$G,$J$3,Movements!$B:$B,$C19,Movements!$A:$A,Stocks!G$1)+SUMIFS(Movements!$I:$I,Movements!$G:$G,$J$6,Movements!$B:$B,$C19,Movements!$A:$A,Stocks!G$1)+SUMIFS(Movements!$I:$I,Movements!$G:$G,$J$7,Movements!$B:$B,$C19,Movements!$A:$A,Stocks!G$1)+SUMIFS(Movements!$I:$I,Movements!$G:$G,$J$8,Movements!$B:$B,$C19,Movements!$A:$A,Stocks!G$1) -> -245.1 | H19: =SUMIFS(Movements!$I:$I,Movements!$G:$G,$J$3,Movements!$B:$B,$C19,Movements!$A:$A,Stocks!H$1)+SUMIFS(Movements!$I:$I,Movements!$G:$G,$J$6,Movements!$B:$B,$C19,Movements!$A:$A,Stocks!H$1)+SUMIFS(Movements!$I:$I,Movements!$G:$G,$J$7,Movements!$B:$B,$C19,Movements!$A:$A,Stocks!H$1)+SUMIFS(Movements!$I:$I,Movements!$G:$G,$J$8,Movements!$B:$B,$C19,Movements!$A:$A,Stocks!H$1) -> -101.9
C20: 657341 | D20: Raw Peanut | E20: =SUMIFS(Movements!$I:$I,Movements!$G:$G,$J$3,Movements!$B:$B,$C20,Movements!$A:$A,Stocks!E$1)+SUMIFS(Movements!$I:$I,Movements!$G:$G,$J$6,Movements!$B:$B,$C20,Movements!$A:$A,Stocks!E$1)+SUMIFS(Movements!$I:$I,Movements!$G:$G,$J$7,Movements!$B:$B,$C20,Movements!$A:$A,Stocks!E$1)+SUMIFS(Movements!$I:$I,Movements!$G:$G,$J$8,Movements!$B:$B,$C20,Movements!$A:$A,Stocks!E$1) -> 0 | F20: =SUMIFS(Movements!$I:$I,Movements!$G:$G,$J$3,Movements!$B:$B,$C20,Movements!$A:$A,Stocks!F$1)+SUMIFS(Movements!$I:$I,Movements!$G:$G,$J$6,Movements!$B:$B,$C20,Movements!$A:$A,Stocks!F$1)+SUMIFS(Movements!$I:$I,Movements!$G:$G,$J$7,Movements!$B:$B,$C20,Movements!$A:$A,Stocks!F$1)+SUMIFS(Movements!$I:$I,Movements!$G:$G,$J$8,Movements!$B:$B,$C20,Movements!$A:$A,Stocks!F$1) -> -122.6925 | G20: =SUMIFS(Movements!$I:$I,Movements!$G:$G,$J$3,Movements!$B:$B,$C20,Movements!$A:$A,Stocks!G$1)+SUMIFS(Movements!$I:$I,Movements!$G:$G,$J$6,Movements!$B:$B,$C20,Movements!$A:$A,Stocks!G$1)+SUMIFS(Movements!$I:$I,Movements!$G:$G,$J$7,Movements!$B:$B,$C20,Movements!$A:$A,Stocks!G$1)+SUMIFS(Movements!$I:$I,Movements!$G:$G,$J$8,Movements!$B:$B,$C20,Movements!$A:$A,Stocks!G$1) -> -250.8075 | H20: =SUMIFS(Movements!$I:$I,Movements!$G:$G,$J$3,Movements!$B:$B,$C20,Movements!$A:$A,Stocks!H$1)+SUMIFS(Movements!$I:$I,Movements!$G:$G,$J$6,Movements!$B:$B,$C20,Movements!$A:$A,Stocks!H$1)+SUMIFS(Movements!$I:$I,Movements!$G:$G,$J$7,Movements!$B:$B,$C20,Movements!$A:$A,Stocks!H$1)+SUMIFS(Movements!$I:$I,Movements!$G:$G,$J$8,Movements!$B:$B,$C20,Movements!$A:$A,Stocks!H$1) -> -116
C21: 876145 | D21: Fried Peanut | E21: =SUMIFS(Movements!$I:$I,Movements!$G:$G,$J$3,Movements!$B:$B,$C21,Movements!$A:$A,Stocks!E$1)+SUMIFS(Movements!$I:$I,Movements!$G:$G,$J$6,Movements!$B:$B,$C21,Movements!$A:$A,Stocks!E$1)+SUMIFS(Movements!$I:$I,Movements!$G:$G,$J$7,Movements!$B:$B,$C21,Movements!$A:$A,Stocks!E$1)+SUMIFS(Movements!$I:$I,Movements!$G:$G,$J$8,Movements!$B:$B,$C21,Movements!$A:$A,Stocks!E$1) -> 0 | F21: =SUMIFS(Movements!$I:$I,Movements!$G:$G,$J$3,Movements!$B:$B,$C21,Movements!$A:$A,Stocks!F$1)+SUMIFS(Movements!$I:$I,Movements!$G:$G,$J$6,Movements!$B:$B,$C21,Movements!$A:$A,Stocks!F$1)+SUMIFS(Movements!$I:$I,Movements!$G:$G,$J$7,Movements!$B:$B,$C21,Movements!$A:$A,Stocks!F$1)+SUMIFS(Movements!$I:$I,Movements!$G:$G,$J$8,Movements!$B:$B,$C21,Movements!$A:$A,Stocks!F$1) -> -104.55 | G21: =SUMIFS(Movements!$I:$I,Movements!$G:$G,$J$3,Movements!$B:$B,$C21,Movements!$A:$A,Stocks!G$1)+SUMIFS(Movements!$I:$I,Movements!$G:$G,$J$6,Movements!$B:$B,$C21,Movements!$A:$A,Stocks!G$1)+SUMIFS(Movements!$I:$I,Movements!$G:$G,$J$7,Movements!$B:$B,$C21,Movements!$A:$A,Stocks!G$1)+SUMIFS(Movements!$I:$I,Movements!$G:$G,$J$8,Movements!$B:$B,$C21,Movements!$A:$A,Stocks!G$1) -> -167 | H21: =SUMIFS(Movements!$I:$I,Movements!$G:$G,$J$3,Movements!$B:$B,$C21,Movements!$A:$A,Stocks!H$1)+SUMIFS(Movements!$I:$I,Movements!$G:$G,$J$6,Movements!$B:$B,$C21,Movements!$A:$A,Stocks!H$1)+SUMIFS(Movements!$I:$I,Movements!$G:$G,$J$7,Movements!$B:$B,$C21,Movements!$A:$A,Stocks!H$1)+SUMIFS(Movements!$I:$I,Movements!$G:$G,$J$8,Movements!$B:$B,$C21,Movements!$A:$A,Stocks!H$1) -> -143.5
C22: 560196 | D22: Biscuit | E22: =SUMIFS(Movements!$I:$I,Movements!$G:$G,$J$3,Movements!$B:$B,$C22,Movements!$A:$A,Stocks!E$1)+SUMIFS(Movements!$I:$I,Movements!$G:$G,$J$6,Movements!$B:$B,$C22,Movements!$A:$A,Stocks!E$1)+SUMIFS(Movements!$I:$I,Movements!$G:$G,$J$7,Movements!$B:$B,$C22,Movements!$A:$A,Stocks!E$1)+SUMIFS(Movements!$I:$I,Movements!$G:$G,$J$8,Movements!$B:$B,$C22,Movements!$A:$A,Stocks!E$1) -> 0 | F22: =SUMIFS(Movements!$I:$I,Movements!$G:$G,$J$3,Movements!$B:$B,$C22,Movements!$A:$A,Stocks!F$1)+SUMIFS(Movements!$I:$I,Movements!$G:$G,$J$6,Movements!$B:$B,$C22,Movements!$A:$A,Stocks!F$1)+SUMIFS(Movements!$I:$I,Movements!$G:$G,$J$7,Movements!$B:$B,$C22,Movements!$A:$A,Stocks!F$1)+SUMIFS(Movements!$I:$I,Movements!$G:$G,$J$8,Movements!$B:$B,$C22,Movements!$A:$A,Stocks!F$1) -> -340 | G22: =SUMIFS(Movements!$I:$I,Movements!$G:$G,$J$3,Movements!$B:$B,$C22,Movements!$A:$A,Stocks!G$1)+SUMIFS(Movements!$I:$I,Movements!$G:$G,$J$6,Movements!$B:$B,$C22,Movements!$A:$A,Stocks!G$1)+SUMIFS(Movements!$I:$I,Movements!$G:$G,$J$7,Movements!$B:$B,$C22,Movements!$A:$A,Stocks!G$1)+SUMIFS(Movements!$I:$I,Movements!$G:$G,$J$8,Movements!$B:$B,$C22,Movements!$A:$A,Stocks!G$1) -> -481 | H22: =SUMIFS(Movements!$I:$I,Movements!$G:$G,$J$3,Movements!$B:$B,$C22,Movements!$A:$A,Stocks!H$1)+SUMIFS(Movements!$I:$I,Movements!$G:$G,$J$6,Movements!$B:$B,$C22,Movements!$A:$A,Stocks!H$1)+SUMIFS(Movements!$I:$I,Movements!$G:$G,$J$7,Movements!$B:$B,$C22,Movements!$A:$A,Stocks!H$1)+SUMIFS(Movements!$I:$I,Movements!$G:$G,$J$8,Movements!$B:$B,$C22,Movements!$A:$A,Stocks!H$1) -> -98
B23: Closing stock | C23: 120301 | D23: Fint | E23: =E2+E9+E16 -> 0 | F23: =F2+F9+F16 -> 210 | G23: =G2+G9+G16 -> 100 | H23: =H2+H9+H16 -> 0
C24: 156212 | D24: Step | E24: =E3+E10+E17 -> 0 | F24: =F3+F10+F17 -> 500 | G24: =G3+G10+G17 -> 700 | H24: =H3+H10+H17 -> 0
C25: 867156 | D25: Chocolate mass | E25: =E4+E11+E18 -> 2481 | F25: =F4+F11+F18 -> 1933 | G25: =G4+G11+G18 -> 578.6 | H25: =H4+H11+H18 -> 0
C26: 765190 | D26: Caramel | E26: =E5+E12+E19 -> 198 | F26: =F5+F12+F19 -> 247 | G26: =G5+G12+G19 -> 51.9 | H26: =H5+H12+H19 -> 0
C27: 657341 | D27: Raw Peanut | E27: =E6+E13+E20 -> 89.5 | F27: =F6+F13+F20 -> 266.8075 | G27: =G6+G13+G20 -> 66 | H27: =H6+H13+H20 -> 0
C28: 876145 | D28: Fried Peanut | E28: =E7+E14+E21 -> 0 | F28: =F7+F14+F21 -> 5.45 | G28: =G7+G14+G21 -> 43.5 | H28: =H7+H14+H21 -> 0
C29: 560196 | D29: Biscuit | E29: =E8+E15+E22 -> 230 | F29: =F8+F15+F22 -> 390 | G29: =G8+G15+G22 -> 9 | H29: =H8+H15+H22 -> 0

Sheet Sales
A1: Movement type | B1: dispatch
A3: Sum of Quantity | C3: Month | G3: Actuals selling price
A4: Material | B4: Mat descr | C4: November | D4: December | E4: January | G4: Material | H4: Mat descr | I4: November | J4: December | K4: January
A5: 120301 | B5: Fint | C5: -300 | D5: -900 | E5: -800 | G5: 120301 | H5: Fint | I5: 59 | J5: 63 | K5: 65
A6: 156212 | B6: Step | C6: -500 | D6: -1300 | E6: -1000 | G6: 156212 | H6: Step | I6: 35 | J6: 25 | K6: 25
A7: Grand Total | C7: -800 | D7: -2200 | E7: -1800
A9: Revenue
A10: Material | B10: Mat descr | C10: November | D10: December | E10: January
A11: 120301 | B11: Fint | C11: =-C5*I5 -> 17700 | D11: =-D5*J5 -> 56700 | E11: =-E5*K5 -> 52000
A12: 156212 | B12: Step | C12: =-C6*I6 -> 17500 | D12: =-D6*J6 -> 32500 | E12: =-E6*K6 -> 25000
A13: TOTAL SALES | C13: =SUM(C11:C12) -> 35200 | D13: =SUM(D11:D12) -> 89200 | E13: =SUM(E11:E12) -> 77000

Sheet Purchases & PPV
A1: Movement type | B1: reception
A3: Sum of Quantity | C3: Month | H3: Std price | K3: Actual Purchasing price
A4: Material | B4: Mat descr | C4: October | D4: November | E4: December | F4: January | H4: 2022 | I4: 2023 | K4: October | L4: November | M4: December | N4: January
A5: 560196 | B5: Biscuit | C5: 230 | D5: 500 | E5: 100 | F5: 89 | H5: =VLOOKUP(A5,'list of materials'!A:E,5,0) -> 25 | I5: =VLOOKUP(A5,'list of materials'!A:F,6,0) -> 27 | K5: 27 | L5: 26 | M5: 28 | N5: 30
A6: 657341 | B6: Raw Peanut | C6: 89.5 | D6: 300 | E6: 50 | F6: 50 | H6: =VLOOKUP(A6,'list of materials'!A:E,5,0) -> 25 | I6: =VLOOKUP(A6,'list of materials'!A:F,6,0) -> 24 | K6: 25 | L6: 25 | M6: 23 | N6: 20
A7: 765190 | B7: Caramel | C7: 198 | D7: 200 | E7: 50 | F7: 50 | H7: =VLOOKUP(A7,'list of materials'!A:E,5,0) -> 15 | I7: =VLOOKUP(A7,'list of materials'!A:F,6,0) -> 16 | K7: 15 | L7: 15 | M7: 16 | N7: 17
A8: 867156 | B8: Chocolate mass | C8: 2481 | D8: 400 | E8: 100 | F8: 100 | H8: =VLOOKUP(A8,'list of materials'!A:E,5,0) -> 28 | I8: =VLOOKUP(A8,'list of materials'!A:F,6,0) -> 31 | K8: 30 | L8: 31 | M8: 32 | N8: 28
A9: Grand Total | C9: 2998.5 | D9: 1400 | E9: 300 | F9: 289
A11: Reception @ std price | K11: Total Cash outflow
A12: Material | B12: Mat descr | C12: October | D12: November | E12: December | F12: January | K12: October | L12: November | M12: December | N12: January
A13: 560196 | B13: Biscuit | C13: =C5*$H5 -> 5750 | D13: =D5*$H5 -> 12500 | E13: =E5*$H5 -> 2500 | F13: =F5*$I5 -> 2403 | K13: =C5*K5 -> 6210 | L13: =D5*L5 -> 13000 | M13: =E5*M5 -> 2800 | N13: =F5*N5 -> 2670
A14: 657341 | B14: Raw Peanut | C14: =C6*$H6 -> 2237.5 | D14: =D6*$H6 -> 7500 | E14: =E6*$H6 -> 1250 | F14: =F6*$I6 -> 1200 | K14: =C6*K6 -> 2237.5 | L14: =D6*L6 -> 7500 | M14: =E6*M6 -> 1150 | N14: =F6*N6 -> 1000
A15: 765190 | B15: Caramel | C15: =C7*$H7 -> 2970 | D15: =D7*$H7 -> 3000 | E15: =E7*$H7 -> 750 | F15: =F7*$I7 -> 800 | K15: =C7*K7 -> 2970 | L15: =D7*L7 -> 3000 | M15: =E7*M7 -> 800 | N15: =F7*N7 -> 850
A16: 867156 | B16: Chocolate mass | C16: =C8*$H8 -> 69468 | D16: =D8*$H8 -> 11200 | E16: =E8*$H8 -> 2800 | F16: =F8*$I8 -> 3100 | K16: =C8*K8 -> 74430 | L16: =D8*L8 -> 12400 | M16: =E8*M8 -> 3200 | N16: =F8*N8 -> 2800
C17: =SUM(C13:C16) -> 80425.5 | D17: =SUM(D13:D16) -> 34200 | E17: =SUM(E13:E16) -> 7300 | F17: =SUM(F13:F16) -> 7503 | K17: =SUM(K13:K16) -> 85847.5 | L17: =SUM(L13:L16) -> 35900 | M17: =SUM(M13:M16) -> 7950 | N17: =SUM(N13:N16) -> 7320
A18: PPV (purchase price variance)
A19: Material | B19: Mat descr | C19: October | D19: November | E19: December | F19: January
A20: 560196 | B20: Biscuit | C20: =C5*(K5-$H5) -> 460 | D20: =D5*(L5-$H5) -> 500 | E20: =E5*(M5-$H5) -> 300 | F20: =F5*(N5-$I5) -> 267
A21: 657341 | B21: Raw Peanut | C21: =C6*(K6-$H6) -> 0 | D21: =D6*(L6-$H6) -> 0 | E21: =E6*(M6-$H6) -> -100 | F21: =F6*(N6-$I6) -> -200
A22: 765190 | B22: Caramel | C22: =C7*(K7-$H7) -> 0 | D22: =D7*(L7-$H7) -> 0 | E22: =E7*(M7-$H7) -> 50 | F22: =F7*(N7-$I7) -> 50
A23: 867156 | B23: Chocolate mass | C23: =C8*(K8-$H8) -> 4962 | D23: =D8*(L8-$H8) -> 1200 | E23: =E8*(M8-$H8) -> 400 | F23: =F8*(N8-$I8) -> -300
C24: =SUM(C20:C23) -> 5422 | D24: =SUM(D20:D23) -> 1700 | E24: =SUM(E20:E23) -> 650 | F24: =SUM(F20:F23) -> -183

Sheet Stock reval
E1: October | F1: November | G1: December | H1: January | N1: October | O1: November | P1: December | Q1: January
A2: =VLOOKUP(C2,'list of materials'!A:C,3,0) -> FG | B2: Closing stock | C2: 120301 | D2: Fint | E2: =Stocks!E23 -> 0 | F2: =Stocks!F23 -> 210 | G2: =Stocks!G23 -> 100 | H2: =Stocks!H23 -> 0 | J2: =VLOOKUP(L2,'list of materials'!A:C,3,0) -> FG | K2: Std cost | L2: 120301 | M2: Fint | N2: =VLOOKUP($L2,'list of materials'!$A:$F,5,0) -> 27.24775 | O2: =VLOOKUP($L2,'list of materials'!$A:$F,5,0) -> 27.24775 | P2: =VLOOKUP($L2,'list of materials'!$A:$F,6,0) -> 29.2598 | Q2: =VLOOKUP($L2,'list of materials'!$A:$F,6,0) -> 29.2598
A3: =VLOOKUP(C3,'list of materials'!A:C,3,0) -> FG | C3: 156212 | D3: Step | E3: =Stocks!E24 -> 0 | F3: =Stocks!F24 -> 500 | G3: =Stocks!G24 -> 700 | H3: =Stocks!H24 -> 0 | J3: =VLOOKUP(L3,'list of materials'!A:C,3,0) -> FG | L3: 156212 | M3: Step | N3: =VLOOKUP($L3,'list of materials'!$A:$F,5,0) -> 25.945 | O3: =VLOOKUP($L3,'list of materials'!$A:$F,5,0) -> 25.945 | P3: =VLOOKUP($L3,'list of materials'!$A:$F,6,0) -> 28.45 | Q3: =VLOOKUP($L3,'list of materials'!$A:$F,6,0) -> 28.45
A4: =VLOOKUP(C4,'list of materials'!A:C,3,0) -> RM | C4: 867156 | D4: Chocolate mass | E4: =Stocks!E25 -> 2481 | F4: =Stocks!F25 -> 1933 | G4: =Stocks!G25 -> 578.6 | H4: =Stocks!H25 -> 0 | J4: =VLOOKUP(L4,'list of materials'!A:C,3,0) -> RM | L4: 867156 | M4: Chocolate mass | N4: =VLOOKUP($L4,'list of materials'!$A:$F,5,0) -> 28 | O4: =VLOOKUP($L4,'list of materials'!$A:$F,5,0) -> 28 | P4: =VLOOKUP($L4,'list of materials'!$A:$F,6,0) -> 31 | Q4: =VLOOKUP($L4,'list of materials'!$A:$F,6,0) -> 31
A5: =VLOOKUP(C5,'list of materials'!A:C,3,0) -> RM | C5: 765190 | D5: Caramel | E5: =Stocks!E26 -> 198 | F5: =Stocks!F26 -> 247 | G5: =Stocks!G26 -> 51.9 | H5: =Stocks!H26 -> 0 | J5: =VLOOKUP(L5,'list of materials'!A:C,3,0) -> RM | L5: 765190 | M5: Caramel | N5: =VLOOKUP($L5,'list of materials'!$A:$F,5,0) -> 15 | O5: =VLOOKUP($L5,'list of materials'!$A:$F,5,0) -> 15 | P5: =VLOOKUP($L5,'list of materials'!$A:$F,6,0) -> 16 | Q5: =VLOOKUP($L5,'list of materials'!$A:$F,6,0) -> 16
A6: =VLOOKUP(C6,'list of materials'!A:C,3,0) -> RM | C6: 657341 | D6: Raw Peanut | E6: =Stocks!E27 -> 89.5 | F6: =Stocks!F27 -> 266.8075 | G6: =Stocks!G27 -> 66 | H6: =Stocks!H27 -> 0 | J6: =VLOOKUP(L6,'list of materials'!A:C,3,0) -> RM | L6: 657341 | M6: Raw Peanut | N6: =VLOOKUP($L6,'list of materials'!$A:$F,5,0) -> 25 | O6: =VLOOKUP($L6,'list of materials'!$A:$F,5,0) -> 25 | P6: =VLOOKUP($L6,'list of materials'!$A:$F,6,0) -> 24 | Q6: =VLOOKUP($L6,'list of materials'!$A:$F,6,0) -> 24
A7: =VLOOKUP(C7,'list of materials'!A:C,3,0) -> SFG | C7: 876145 | D7: Fried Peanut | E7: =Stocks!E28 -> 0 | F7: =Stocks!F28 -> 5.45 | G7: =Stocks!G28 -> 43.5 | H7: =Stocks!H28 -> 0 | J7: =VLOOKUP(L7,'list of materials'!A:C,3,0) -> SFG | L7: 876145 | M7: Fried Peanut | N7: =VLOOKUP($L7,'list of materials'!$A:$F,5,0) -> 28.75 | O7: =VLOOKUP($L7,'list of materials'!$A:$F,5,0) -> 28.75 | P7: =VLOOKUP($L7,'list of materials'!$A:$F,6,0) -> 27.6 | Q7: =VLOOKUP($L7,'list of materials'!$A:$F,6,0) -> 27.6
A8: =VLOOKUP(C8,'list of materials'!A:C,3,0) -> RM | C8: 560196 | D8: Biscuit | E8: =Stocks!E29 -> 230 | F8: =Stocks!F29 -> 390 | G8: =Stocks!G29 -> 9 | H8: =Stocks!H29 -> 0 | J8: =VLOOKUP(L8,'list of materials'!A:C,3,0) -> RM | L8: 560196 | M8: Biscuit | N8: =VLOOKUP($L8,'list of materials'!$A:$F,5,0) -> 25 | O8: =VLOOKUP($L8,'list of materials'!$A:$F,5,0) -> 25 | P8: =VLOOKUP($L8,'list of materials'!$A:$F,6,0) -> 27 | Q8: =VLOOKUP($L8,'list of materials'!$A:$F,6,0) -> 27
A10: =VLOOKUP(C10,'list of materials'!A:C,3,0) -> FG | B10: Reevaluated cost | C10: 120301 | D10: Fint | E10: =M18 -> 28.66375 | F10: =N18 -> 29.37175 | G10: =O18 -> 29.71025 | H10: =P18 -> 26.273
A11: =VLOOKUP(C11,'list of materials'!A:C,3,0) -> FG | C11: 156212 | D11: Step | E11: =M32 -> 27.765 | F11: =N32 -> 28.035 | G11: =O32 -> 29.36 | H11: =P32 -> 27.735
A12: =VLOOKUP(C12,'list of materials'!A:C,3,0) -> RM | C12: 867156 | D12: Chocolate mass | E12: ='Purchases & PPV'!K8 -> 30 | F12: ='Purchases & PPV'!L8 -> 31 | G12: ='Purchases & PPV'!M8 -> 32 | H12: ='Purchases & PPV'!N8 -> 28 | K12: FINT
A13: =VLOOKUP(C13,'list of materials'!A:C,3,0) -> RM | C13: 765190 | D13: Caramel | E13: ='Purchases & PPV'!K7 -> 15 | F13: ='Purchases & PPV'!L7 -> 15 | G13: ='Purchases & PPV'!M7 -> 16 | H13: ='Purchases & PPV'!N7 -> 17 | K13: cost breakdown | M13: Reevaluated cost
A14: =VLOOKUP(C14,'list of materials'!A:C,3,0) -> RM | C14: 657341 | D14: Raw Peanut | E14: ='Purchases & PPV'!K6 -> 25 | F14: ='Purchases & PPV'!L6 -> 25 | G14: ='Purchases & PPV'!M6 -> 23 | H14: ='Purchases & PPV'!N6 -> 20 | K14: 1000 | L14: kg | M14: October | N14: November | O14: December | P14: January
A15: =VLOOKUP(C15,'list of materials'!A:C,3,0) -> SFG | C15: 876145 | D15: Fried Peanut | E15: =M24 -> 28.75 | F15: =N24 -> 28.75 | G15: =O24 -> 26.45 | H15: =P24 -> 23 | K15: Chocolate mass | L15: ='BOM & Std price'!L3 -> 708 | M15: =E12 -> 30 | N15: =F12 -> 31 | O15: =G12 -> 32 | P15: =H12 -> 28
A16: =VLOOKUP(C16,'list of materials'!A:C,3,0) -> RM | C16: 560196 | D16: Biscuit | E16: ='Purchases & PPV'!K5 -> 27 | F16: ='Purchases & PPV'!L5 -> 26 | G16: ='Purchases & PPV'!M5 -> 28 | H16: ='Purchases & PPV'!N5 -> 30 | K16: Fried Peanut | L16: ='BOM & Std price'!L4 -> 205 | M16: =E15 -> 28.75 | N16: =F15 -> 28.75 | O16: =G15 -> 26.45 | P16: =H15 -> 23
K17: Caramel | L17: ='BOM & Std price'!L5 -> 102 | M17: =E13 -> 15 | N17: =F13 -> 15 | O17: =G13 -> 16 | P17: =H13 -> 17
A18: =VLOOKUP(C18,'list of materials'!A:C,3,0) -> FG | B18: Stock reevaluation | C18: 120301 | D18: Fint | E18: =(E10-N2)*E2 -> 0 | F18: =(F10-O2)*F2 -> 446.04 | G18: =(G10-P2)*G2 -> 45.045 | H18: =(H10-Q2)*H2 -> 0 | K18: Cost per 1 kg | M18: =SUMPRODUCT(M15:M17,$L$15:$L$17)/$K$14 -> 28.66375 | N18: =SUMPRODUCT(N15:N17,$L$15:$L$17)/$K$14 -> 29.37175 | O18: =SUMPRODUCT(O15:O17,$L$15:$L$17)/$K$14 -> 29.71025 | P18: =SUMPRODUCT(P15:P17,$L$15:$L$17)/$K$14 -> 26.273
A19: =VLOOKUP(C19,'list of materials'!A:C,3,0) -> FG | C19: 156212 | D19: Step | E19: =(E11-N3)*E3 -> 0 | F19: =(F11-O3)*F3 -> 1045 | G19: =(G11-P3)*G3 -> 637 | H19: =(H11-Q3)*H3 -> 0
A20: =VLOOKUP(C20,'list of materials'!A:C,3,0) -> RM | C20: 867156 | D20: Chocolate mass | E20: =(E12-N4)*E4 -> 4962 | F20: =(F12-O4)*F4 -> 5799 | G20: =(G12-P4)*G4 -> 578.6 | H20: =(H12-Q4)*H4 -> 0 | K20: Fried Peanut
A21: =VLOOKUP(C21,'list of materials'!A:C,3,0) -> RM | C21: 765190 | D21: Caramel | E21: =(E13-N5)*E5 -> 0 | F21: =(F13-O5)*F5 -> 0 | G21: =(G13-P5)*G5 -> 0 | H21: =(H13-Q5)*H5 -> 0 | K21: cost breakdown | M21: Reevaluated cost
A22: =VLOOKUP(C22,'list of materials'!A:C,3,0) -> RM | C22: 657341 | D22: Raw Peanut | E22: =(E14-N6)*E6 -> 0 | F22: =(F14-O6)*F6 -> 0 | G22: =(G14-P6)*G6 -> -66 | H22: =(H14-Q6)*H6 -> 0 | K22: 1000 | L22: kg | M22: October | N22: November | O22: December | P22: January
A23: =VLOOKUP(C23,'list of materials'!A:C,3,0) -> SFG | C23: 876145 | D23: Fried Peanut | E23: =(E15-N7)*E7 -> 0 | F23: =(F15-O7)*F7 -> 0 | G23: =(G15-P7)*G7 -> -50.025 | H23: =(H15-Q7)*H7 -> 0 | K23: Chocolate mass | L23: ='BOM & Std price'!L15 -> 1150 | M23: =E14 -> 25 | N23: =F14 -> 25 | O23: =G14 -> 23 | P23: =H14 -> 20
A24: =VLOOKUP(C24,'list of materials'!A:C,3,0) -> RM | C24: 560196 | D24: Biscuit | E24: =(E16-N8)*E8 -> 460 | F24: =(F16-O8)*F8 -> 390 | G24: =(G16-P8)*G8 -> 9 | H24: =(H16-Q8)*H8 -> 0 | K24: Cost per 1 kg | M24: =M23*$L$23/$K$22 -> 28.75 | N24: =N23*$L$23/$K$22 -> 28.75 | O24: =O23*$L$23/$K$22 -> 26.45 | P24: =P23*$L$23/$K$22 -> 23
A26: RM | B26: Provision | E26: =SUMIFS(E$18:E$24,$A$18:$A$24,$A26) -> 5422 | F26: =SUMIFS(F$18:F$24,$A$18:$A$24,$A26) -> 6189 | G26: =SUMIFS(G$18:G$24,$A$18:$A$24,$A26) -> 521.6 | H26: =SUMIFS(H$18:H$24,$A$18:$A$24,$A26) -> 0 | K26: STEP
A27: RM | B27: Change in Std cost 23 vs 22 | G27: =G4*(P4-O4)+G5*(P5-O5)+G6*(P6-O6)+G8*(P8-O8) -> 1739.7 | K27: cost breakdown | M27: Reevaluated cost
B28: Reversal | F28: =-E26 -> -5422 | G28: =-F26 -> -6189 | H28: =-G26 -> -521.6 | K28: 1000 | L28: kg | M28: October | N28: November | O28: December | P28: January
B29: Total | E29: =SUM(E26:E28) -> 5422 | F29: =SUM(F26:F28) -> 767 | G29: =SUM(G26:G28) -> -3927.7 | H29: =SUM(H26:H28) -> -521.6 | K29: ='BOM & Std price'!K25 -> Chocolate mass | L29: ='BOM & Std price'!L25 -> 590 | M29: =E12 -> 30 | N29: =F12 -> 31 | O29: =G12 -> 32 | P29: =H12 -> 28
K30: ='BOM & Std price'!K26 -> Biscuit | L30: ='BOM & Std price'!L26 -> 320 | M30: =E16 -> 27 | N30: =F16 -> 26 | O30: =G16 -> 28 | P30: =H16 -> 30
A31: SFG | B31: Provision | E31: =SUMIFS(E$18:E$24,$A$18:$A$24,$A31) -> 0 | F31: =SUMIFS(F$18:F$24,$A$18:$A$24,$A31) -> 0 | G31: =SUMIFS(G$18:G$24,$A$18:$A$24,$A31) -> -50.025 | H31: =SUMIFS(H$18:H$24,$A$18:$A$24,$A31) -> 0 | K31: ='BOM & Std price'!K27 -> Caramel | L31: ='BOM & Std price'!L27 -> 95 | M31: =E13 -> 15 | N31: =F13 -> 15 | O31: =G13 -> 16 | P31: =H13 -> 17
A32: SFG | B32: Change in Std cost 23 vs 22 | G32: =G7*(P7-O7) -> -50.025 | K32: Cost per 1 kg | M32: =SUMPRODUCT(M29:M31,$L$29:$L$31)/$K$28 -> 27.765 | N32: =SUMPRODUCT(N29:N31,$L$29:$L$31)/$K$28 -> 28.035 | O32: =SUMPRODUCT(O29:O31,$L$29:$L$31)/$K$28 -> 29.36 | P32: =SUMPRODUCT(P29:P31,$L$29:$L$31)/$K$28 -> 27.735
B33: Reversal | F33: =-E31 -> 0 | G33: =-F31 -> 0 | H33: =-G31 -> 50.025
B34: Total | E34: =SUM(E31:E33) -> 0 | F34: =SUM(F31:F33) -> 0 | G34: =SUM(G31:G33) -> -100.05 | H34: =SUM(H31:H33) -> 50.025
A36: FG | B36: Provision | E36: =SUMIFS(E$18:E$24,$A$18:$A$24,$A36) -> 0 | F36: =SUMIFS(F$18:F$24,$A$18:$A$24,$A36) -> 1491.04 | G36: =SUMIFS(G$18:G$24,$A$18:$A$24,$A36) -> 682.045 | H36: =SUMIFS(H$18:H$24,$A$18:$A$24,$A36) -> 0
A37: FG | B37: Change in Std cost 23 vs 22 | G37: =G2*(P2-O2)+G3*(P3-O3) -> 1954.705
B38: Reversal | F38: =-E36 -> 0 | G38: =-F36 -> -1491.04 | H38: =-G36 -> -682.045
B39: Total | E39: =SUM(E36:E38) -> 0 | F39: =SUM(F36:F38) -> 1491.04 | G39: =SUM(G36:G38) -> 1145.71 | H39: =SUM(H36:H38) -> -682.045

Sheet Formulation & overusage
C2: Step | J2: per | K2: 1000 | L2: kg
D3: October | E3: November | F3: December | G3: January | I3: Mat type | J3: Alternative | K3: Mat number | L3: ='BOM & Std price'!D28 -> Std'22 | M3: ='BOM & Std price'!E28 -> Oct act | N3: ='BOM & Std price'!F28 -> Nov act | O3: ='BOM & Std price'!G28 -> Dec act | P3: ='BOM & Std price'!H28 -> Std'23 | Q3: ='BOM & Std price'!I28 -> Jan act
A4: P | C4: Actual output | D4: =SUMIFS(Movements!$I:$I,Movements!$G:$G,$A4,Movements!$A:$A,D$3,Movements!$C:$C,'Formulation & overusage'!$C$2) -> 0 | E4: =SUMIFS(Movements!$I:$I,Movements!$G:$G,$A4,Movements!$A:$A,E$3,Movements!$C:$C,'Formulation & overusage'!$C$2) -> 1000 | F4: =SUMIFS(Movements!$I:$I,Movements!$G:$G,$A4,Movements!$A:$A,F$3,Movements!$C:$C,'Formulation & overusage'!$C$2) -> 1500 | G4: =SUMIFS(Movements!$I:$I,Movements!$G:$G,$A4,Movements!$A:$A,G$3,Movements!$C:$C,'Formulation & overusage'!$C$2) -> 303 | I4: RM | J4: Chocolate mass | K4: ='BOM & Std price'!C29 -> 867156 | L4: 590 | M4: ='BOM & Std price'!E29 -> 590 | N4: ='BOM & Std price'!F29 -> 590 | O4: ='BOM & Std price'!G29 -> 590 | P4: ='BOM & Std price'!H29 -> 590 | Q4: ='BOM & Std price'!I29 -> 590
I5: RM | J5: Biscuit | K5: ='BOM & Std price'!C30 -> 560196 | L5: 320 | M5: ='BOM & Std price'!E30 -> 320 | N5: ='BOM & Std price'!F30 -> 320 | O5: ='BOM & Std price'!G30 -> 320 | P5: ='BOM & Std price'!H30 -> 320 | Q5: ='BOM & Std price'!I30 -> 320
A6: Consumption @ std BOM | B6: =I4 -> RM | C6: =J4 -> Chocolate mass | D6: =$L4/$K$2*D$4 -> 0 | E6: =$L4/$K$2*E$4 -> 590 | F6: =$L4/$K$2*F$4 -> 885 | G6: =$P4/$K$2*G$4 -> 178.77 | I6: RM | J6: Caramel | K6: ='BOM & Std price'!C31 -> 765190 | L6: 95 | M6: ='BOM & Std price'!E31 -> 95 | N6: ='BOM & Std price'!F31 -> 95 | O6: ='BOM & Std price'!G31 -> 95 | P6: ='BOM & Std price'!H31 -> 95 | Q6: ='BOM & Std price'!I31 -> 95
B7: =I5 -> RM | C7: =J5 -> Biscuit | D7: =$L5/$K$2*D$4 -> 0 | E7: =$L5/$K$2*E$4 -> 320 | F7: =$L5/$K$2*F$4 -> 480 | G7: =$P5/$K$2*G$4 -> 96.96 | J7: Total | L7: =SUM(L4:L6) -> 1005 | M7: ='BOM & Std price'!E32 -> 1005 | N7: ='BOM & Std price'!F32 -> 1005 | O7: ='BOM & Std price'!G32 -> 1005 | P7: ='BOM & Std price'!H32 -> 1005 | Q7: ='BOM & Std price'!I32 -> 1005
B8: =I6 -> RM | C8: =J6 -> Caramel | D8: =$L6/$K$2*D$4 -> 0 | E8: =$L6/$K$2*E$4 -> 95 | F8: =$L6/$K$2*F$4 -> 142.5 | G8: =$P6/$K$2*G$4 -> 28.785 | J8: Designed process loss | L8: =L7/$K$2-1 -> 0.005 | M8: ='BOM & Std price'!E33 -> 0.005 | N8: ='BOM & Std price'!F33 -> 0.005 | O8: ='BOM & Std price'!G33 -> 0.005 | P8: ='BOM & Std price'!H33 -> 0.005 | Q8: ='BOM & Std price'!I33 -> 0.005
A10: Consumption @ act BOM | B10: =I4 -> RM | C10: =J4 -> Chocolate mass | D10: =M4/$K$2*D$4 -> 0 | E10: =N4/$K$2*E$4 -> 590 | F10: =O4/$K$2*F$4 -> 885 | G10: =Q4/$K$2*G$4 -> 178.77
B11: =I5 -> RM | C11: =J5 -> Biscuit | D11: =M5/$K$2*D$4 -> 0 | E11: =N5/$K$2*E$4 -> 320 | F11: =O5/$K$2*F$4 -> 480 | G11: =Q5/$K$2*G$4 -> 96.96
B12: =I6 -> RM | C12: =J6 -> Caramel | D12: =M6/$K$2*D$4 -> 0 | E12: =N6/$K$2*E$4 -> 95 | F12: =O6/$K$2*F$4 -> 142.5 | G12: =Q6/$K$2*G$4 -> 28.785
J13: Standard price | K13: Mat number | M13: October | N13: November | O13: December | P13: January
A14: Formulation variance Qty | B14: =I4 -> RM | C14: =J4 -> Chocolate mass | D14: =D10-D6 -> 0 | E14: =E10-E6 -> 0 | F14: =F10-F6 -> 0 | G14: =G10-G6 -> 0 | J14: =J4 -> Chocolate mass | K14: 867156 | M14: =VLOOKUP($K14,'list of materials'!$A:$F,5,0) -> 28 | N14: =VLOOKUP($K14,'list of materials'!$A:$F,5,0) -> 28 | O14: =VLOOKUP($K14,'list of materials'!$A:$F,5,0) -> 28 | P14: =VLOOKUP($K14,'list of materials'!$A:$F,6,0) -> 31
B15: =I5 -> RM | C15: =J5 -> Biscuit | D15: =D11-D7 -> 0 | E15: =E11-E7 -> 0 | F15: =F11-F7 -> 0 | G15: =G11-G7 -> 0 | J15: =J5 -> Biscuit | K15: 560196 | M15: =VLOOKUP($K15,'list of materials'!$A:$F,5,0) -> 25 | N15: =VLOOKUP($K15,'list of materials'!$A:$F,5,0) -> 25 | O15: =VLOOKUP($K15,'list of materials'!$A:$F,5,0) -> 25 | P15: =VLOOKUP($K15,'list of materials'!$A:$F,6,0) -> 27
B16: =I6 -> RM | C16: =J6 -> Caramel | D16: =D12-D8 -> 0 | E16: =E12-E8 -> 0 | F16: =F12-F8 -> 0 | G16: =G12-G8 -> 0 | J16: =J6 -> Caramel | K16: 765190 | M16: =VLOOKUP($K16,'list of materials'!$A:$F,5,0) -> 15 | N16: =VLOOKUP($K16,'list of materials'!$A:$F,5,0) -> 15 | O16: =VLOOKUP($K16,'list of materials'!$A:$F,5,0) -> 15 | P16: =VLOOKUP($K16,'list of materials'!$A:$F,6,0) -> 16
A18: Formulation var currency | B18: =I4 -> RM | C18: =J4 -> Chocolate mass | D18: =D14*M14 -> 0 | E18: =E14*N14 -> 0 | F18: =F14*O14 -> 0 | G18: =G14*P14 -> 0
B19: =I5 -> RM | C19: =J5 -> Biscuit | D19: =D15*M15 -> 0 | E19: =E15*N15 -> 0 | F19: =F15*O15 -> 0 | G19: =G15*P15 -> 0
B20: =I6 -> RM | C20: =J6 -> Caramel | D20: =D16*M16 -> 0 | E20: =E16*N16 -> 0 | F20: =F16*O16 -> 0 | G20: =G16*P16 -> 0
A22: Actual consumption Qty | B22: =I4 -> RM | C22: =J4 -> Chocolate mass | D22: =-SUMIFS(Movements!$I:$I,Movements!$A:$A,D$3,Movements!$G:$G,$A$23,Movements!$C:$C,'Formulation & overusage'!$C22,Movements!$E:$E,'Formulation & overusage'!$A$24) -> 0 | E22: =-SUMIFS(Movements!$I:$I,Movements!$A:$A,E$3,Movements!$G:$G,$A$23,Movements!$C:$C,'Formulation & overusage'!$C22,Movements!$E:$E,'Formulation & overusage'!$A$24) -> 590 | F22: =-SUMIFS(Movements!$I:$I,Movements!$A:$A,F$3,Movements!$G:$G,$A$23,Movements!$C:$C,'Formulation & overusage'!$C22,Movements!$E:$E,'Formulation & overusage'!$A$24) -> 885 | G22: =-SUMIFS(Movements!$I:$I,Movements!$A:$A,G$3,Movements!$G:$G,$A$23,Movements!$C:$C,'Formulation & overusage'!$C22,Movements!$E:$E,'Formulation & overusage'!$A$24) -> 177
A23: C | B23: =I5 -> RM | C23: =J5 -> Biscuit | D23: =-SUMIFS(Movements!$I:$I,Movements!$A:$A,D$3,Movements!$G:$G,$A$23,Movements!$C:$C,'Formulation & overusage'!$C23,Movements!$E:$E,'Formulation & overusage'!$A$24) -> 0 | E23: =-SUMIFS(Movements!$I:$I,Movements!$A:$A,E$3,Movements!$G:$G,$A$23,Movements!$C:$C,'Formulation & overusage'!$C23,Movements!$E:$E,'Formulation & overusage'!$A$24) -> 320 | F23: =-SUMIFS(Movements!$I:$I,Movements!$A:$A,F$3,Movements!$G:$G,$A$23,Movements!$C:$C,'Formulation & overusage'!$C23,Movements!$E:$E,'Formulation & overusage'!$A$24) -> 480 | G23: =-SUMIFS(Movements!$I:$I,Movements!$A:$A,G$3,Movements!$G:$G,$A$23,Movements!$C:$C,'Formulation & overusage'!$C23,Movements!$E:$E,'Formulation & overusage'!$A$24) -> 96
A24: Step L | B24: =I6 -> RM | C24: =J6 -> Caramel | D24: =-SUMIFS(Movements!$I:$I,Movements!$A:$A,D$3,Movements!$G:$G,$A$23,Movements!$C:$C,'Formulation & overusage'!$C24,Movements!$E:$E,'Formulation & overusage'!$A$24) -> 0 | E24: =-SUMIFS(Movements!$I:$I,Movements!$A:$A,E$3,Movements!$G:$G,$A$23,Movements!$C:$C,'Formulation & overusage'!$C24,Movements!$E:$E,'Formulation & overusage'!$A$24) -> 95 | F24: =-SUMIFS(Movements!$I:$I,Movements!$A:$A,F$3,Movements!$G:$G,$A$23,Movements!$C:$C,'Formulation & overusage'!$C24,Movements!$E:$E,'Formulation & overusage'!$A$24) -> 142.5 | G24: =-SUMIFS(Movements!$I:$I,Movements!$A:$A,G$3,Movements!$G:$G,$A$23,Movements!$C:$C,'Formulation & overusage'!$C24,Movements!$E:$E,'Formulation & overusage'!$A$24) -> 28.5
A26: Usage variance Qty | B26: =I4 -> RM | C26: =J4 -> Chocolate mass | D26: =D22-D10 -> 0 | E26: =E22-E10 -> 0 | F26: =F22-F10 -> 0 | G26: =G22-G10 -> -1.77
B27: =I5 -> RM | C27: =J5 -> Biscuit | D27: =D23-D11 -> 0 | E27: =E23-E11 -> 0 | F27: =F23-F11 -> 0 | G27: =G23-G11 -> -0.96
B28: =I6 -> RM | C28: =J6 -> Caramel | D28: =D24-D12 -> 0 | E28: =E24-E12 -> 0 | F28: =F24-F12 -> 0 | G28: =G24-G12 -> -0.285
A30: Usage variance currency | B30: =I4 -> RM | C30: =J4 -> Chocolate mass | D30: =D26*M14 -> 0 | E30: =E26*N14 -> 0 | F30: =F26*O14 -> 0 | G30: =G26*P14 -> -54.87
B31: =I5 -> RM | C31: =J5 -> Biscuit | D31: =D27*M15 -> 0 | E31: =E27*N15 -> 0 | F31: =F27*O15 -> 0 | G31: =G27*P15 -> -25.92
B32: =I6 -> RM | C32: =J6 -> Caramel | D32: =D28*M16 -> 0 | E32: =E28*N16 -> 0 | F32: =F28*O16 -> 0 | G32: =G28*P16 -> -4.56
C34: Fried Peanut | J34: per | K34: 1000 | L34: kg
D35: October | E35: November | F35: December | G35: January | I35: Mat type | J35: Alternative | K35: Mat number | L35: ='BOM & Std price'!D17 -> Std'22 | M35: ='BOM & Std price'!E17 -> Oct act | N35: ='BOM & Std price'!F17 -> Nov act | O35: ='BOM & Std price'!G17 -> Dec act | P35: ='BOM & Std price'!H17 -> Std'23 | Q35: ='BOM & Std price'!I17 -> Jan act
A36: P | C36: Actual output | D36: =SUMIFS(Movements!$I:$I,Movements!$G:$G,$A36,Movements!$A:$A,D$3,Movements!$C:$C,'Formulation & overusage'!$C$34) -> 0 | E36: =SUMIFS(Movements!$I:$I,Movements!$G:$G,$A36,Movements!$A:$A,E$3,Movements!$C:$C,'Formulation & overusage'!$C$34) -> 110 | F36: =SUMIFS(Movements!$I:$I,Movements!$G:$G,$A36,Movements!$A:$A,F$3,Movements!$C:$C,'Formulation & overusage'!$C$34) -> 205.05 | G36: =SUMIFS(Movements!$I:$I,Movements!$G:$G,$A36,Movements!$A:$A,G$3,Movements!$C:$C,'Formulation & overusage'!$C$34) -> 100 | I36: RM | J36: Raw Peanut | K36: ='BOM & Std price'!C18 -> 657341 | L36: ='BOM & Std price'!D18 -> 1150 | M36: ='BOM & Std price'!E18 -> 1150 | N36: ='BOM & Std price'!F18 -> 1150 | O36: ='BOM & Std price'!G18 -> 1150 | P36: ='BOM & Std price'!H18 -> 1150 | Q36: ='BOM & Std price'!I18 -> 1150
J37: Total | L37: ='BOM & Std price'!D19 -> 1150 | M37: ='BOM & Std price'!E19 -> 1150 | N37: ='BOM & Std price'!F19 -> 1150 | O37: ='BOM & Std price'!G19 -> 1150 | P37: ='BOM & Std price'!H19 -> 1150 | Q37: ='BOM & Std price'!I19 -> 1150
A38: Consumption @ std BOM | B38: =I36 -> RM | C38: =J36 -> Raw Peanut | D38: =$L36/$K$34*D$36 -> 0 | E38: =$L36/$K$34*E$36 -> 126.5 | F38: =$L36/$K$34*F$36 -> 235.8075 | G38: =$P36/$K$34*G$36 -> 115 | J38: Designed process loss | L38: =L37/$K$34-1 -> 0.15 | M38: =M37/$K$34-1 -> 0.15 | N38: =N37/$K$34-1 -> 0.15 | O38: =O37/$K$34-1 -> 0.15 | P38: =P37/$K$34-1 -> 0.15 | Q38: =Q37/$K$34-1 -> 0.15
A40: Consumption @ act BOM | B40: =I36 -> RM | C40: =J36 -> Raw Peanut | D40: =M36/$K$34*D$36 -> 0 | E40: =N36/$K$34*E$36 -> 126.5 | F40: =O36/$K$34*F$36 -> 235.8075 | G40: =Q36/$K$34*G$36 -> 115 | J40: Standard price | M40: October | N40: November | O40: December | P40: January
J41: =J36 -> Raw Peanut | K41: =K36 -> 657341 | M41: =VLOOKUP($K41,'list of materials'!$A:$F,5,0) -> 25 | N41: =VLOOKUP($K41,'list of materials'!$A:$F,5,0) -> 25 | O41: =VLOOKUP($K41,'list of materials'!$A:$F,5,0) -> 25 | P41: =VLOOKUP($K41,'list of materials'!$A:$F,6,0) -> 24
A42: Formulation variance Qty | B42: =I36 -> RM | C42: =J36 -> Raw Peanut | D42: =D40-D38 -> 0 | E42: =E40-E38 -> 0 | F42: =F40-F38 -> 0 | G42: =G40-G38 -> 0
A44: Formulation var currency | B44: =I36 -> RM | C44: =J36 -> Raw Peanut | D44: =D42*M41 -> 0 | E44: =E42*N41 -> 0 | F44: =F42*O41 -> 0 | G44: =G42*P41 -> 0
A46: Actual consumption Qty | B46: =I36 -> RM | C46: =J36 -> Raw Peanut | D46: =-SUMIFS(Movements!$I:$I,Movements!$A:$A,D$35,Movements!$G:$G,$A$47,Movements!$C:$C,'Formulation & overusage'!$C46,Movements!$E:$E,'Formulation & overusage'!$A$48) -> 0 | E46: =-SUMIFS(Movements!$I:$I,Movements!$A:$A,E$35,Movements!$G:$G,$A$47,Movements!$C:$C,'Formulation & overusage'!$C46,Movements!$E:$E,'Formulation & overusage'!$A$48) -> 120.6925 | F46: =-SUMIFS(Movements!$I:$I,Movements!$A:$A,F$35,Movements!$G:$G,$A$47,Movements!$C:$C,'Formulation & overusage'!$C46,Movements!$E:$E,'Formulation & overusage'!$A$48) -> 235.8075 | G46: =-SUMIFS(Movements!$I:$I,Movements!$A:$A,G$35,Movements!$G:$G,$A$47,Movements!$C:$C,'Formulation & overusage'!$C46,Movements!$E:$E,'Formulation & overusage'!$A$48) -> 115
A47: C
A48: NP
A50: Usage variance Qty | B50: =I36 -> RM | C50: =J36 -> Raw Peanut | D50: =D46-D40 -> 0 | E50: =E46-E40 -> -5.8075 | F50: =F46-F40 -> 0 | G50: =G46-G40 -> 0
A52: Usage variance currency | B52: =I36 -> RM | C52: =J36 -> Raw Peanut | D52: =D50*M41 -> 0 | E52: =E50*N41 -> -145.1875 | F52: =F50*O41 -> 0 | G52: =G50*P41 -> 0
C54: Fint | J54: per | K54: 1000 | L54: kg
D55: October | E55: November | F55: December | G55: January | I55: Mat type | J55: Alternative | K55: Mat number | L55: ='BOM & Std price'!D6 -> Std'22 | M55: ='BOM & Std price'!E6 -> Oct act | N55: ='BOM & Std price'!F6 -> Nov act | O55: ='BOM & Std price'!G6 -> Dec act | P55: ='BOM & Std price'!H6 -> Std'23 | Q55: ='BOM & Std price'!I6 -> Jan act
A56: P | C56: Actual output | D56: =SUMIFS(Movements!$I:$I,Movements!$G:$G,$A56,Movements!$A:$A,D$55,Movements!$C:$C,'Formulation & overusage'!$C$54) -> 0 | E56: =SUMIFS(Movements!$I:$I,Movements!$G:$G,$A56,Movements!$A:$A,E$55,Movements!$C:$C,'Formulation & overusage'!$C$54) -> 510 | F56: =SUMIFS(Movements!$I:$I,Movements!$G:$G,$A56,Movements!$A:$A,F$55,Movements!$C:$C,'Formulation & overusage'!$C$54) -> 800 | G56: =SUMIFS(Movements!$I:$I,Movements!$G:$G,$A56,Movements!$A:$A,G$55,Movements!$C:$C,'Formulation & overusage'!$C$54) -> 700 | I56: RM | J56: Chocolate mass | K56: ='BOM & Std price'!C7 -> 867156 | L56: ='BOM & Std price'!D7 -> 708 | M56: ='BOM & Std price'!E7 -> 708 | N56: ='BOM & Std price'!F7 -> 711 | O56: ='BOM & Std price'!G7 -> 711 | P56: ='BOM & Std price'!H7 -> 711 | Q56: ='BOM & Std price'!I7 -> 708
I57: SFG | J57: Fried Peanut | K57: ='BOM & Std price'!C8 -> 876145 | L57: ='BOM & Std price'!D8 -> 205 | M57: ='BOM & Std price'!E8 -> 205 | N57: ='BOM & Std price'!F8 -> 203 | O57: ='BOM & Std price'!G8 -> 203 | P57: ='BOM & Std price'!H8 -> 203 | Q57: ='BOM & Std price'!I8 -> 205
A58: Consumption @ std BOM | B58: =I56 -> RM | C58: =J56 -> Chocolate mass | D58: =$L56/$K$54*D$56 -> 0 | E58: =$L56/$K$54*E$56 -> 361.08 | F58: =$L56/$K$54*F$56 -> 566.4 | G58: =$P56/$K$54*G$56 -> 497.7 | I58: RM | J58: Caramel | K58: ='BOM & Std price'!C9 -> 765190 | L58: ='BOM & Std price'!D9 -> 102 | M58: ='BOM & Std price'!E9 -> 102 | N58: ='BOM & Std price'!F9 -> 101 | O58: ='BOM & Std price'!G9 -> 101 | P58: ='BOM & Std price'!H9 -> 101 | Q58: ='BOM & Std price'!I9 -> 102
B59: =I57 -> SFG | C59: =J57 -> Fried Peanut | D59: =$L57/$K$54*D$56 -> 0 | E59: =$L57/$K$54*E$56 -> 104.55 | F59: =$L57/$K$54*F$56 -> 164 | G59: =$P57/$K$54*G$56 -> 142.1 | J59: Total | L59: ='BOM & Std price'!D10 -> 1015 | M59: ='BOM & Std price'!E10 -> 1015 | N59: ='BOM & Std price'!F10 -> 1015 | O59: ='BOM & Std price'!G10 -> 1015 | P59: ='BOM & Std price'!H10 -> 1015 | Q59: ='BOM & Std price'!I10 -> 1015
B60: =I58 -> RM | C60: =J58 -> Caramel | D60: =$L58/$K$54*D$56 -> 0 | E60: =$L58/$K$54*E$56 -> 52.02 | F60: =$L58/$K$54*F$56 -> 81.6 | G60: =$P58/$K$54*G$56 -> 70.7 | J60: Designed process loss | L60: =L59/$K$54-1 -> 0.015 | M60: =M59/$K$54-1 -> 0.015 | N60: =N59/$K$54-1 -> 0.015 | O60: =O59/$K$54-1 -> 0.015 | P60: =P59/$K$54-1 -> 0.015 | Q60: =Q59/$K$54-1 -> 0.015
A62: Consumption @ act BOM | B62: =I56 -> RM | C62: =J56 -> Chocolate mass | D62: =M56/$K$54*D$56 -> 0 | E62: =N56/$K$54*E$56 -> 362.61 | F62: =O56/$K$54*F$56 -> 568.8 | G62: =Q56/$K$54*G$56 -> 495.6
B63: =I57 -> SFG | C63: =J57 -> Fried Peanut | D63: =M57/$K$54*D$56 -> 0 | E63: =N57/$K$54*E$56 -> 103.53 | F63: =O57/$K$54*F$56 -> 162.4 | G63: =Q57/$K$54*G$56 -> 143.5
B64: =I58 -> RM | C64: =J58 -> Caramel | D64: =M58/$K$54*D$56 -> 0 | E64: =N58/$K$54*E$56 -> 51.51 | F64: =O58/$K$54*F$56 -> 80.8 | G64: =Q58/$K$54*G$56 -> 71.4
J65: Standard price | K65: Mat number | M65: October | N65: November | O65: December | P65: January
A66: Formulation variance Qty | B66: =I56 -> RM | C66: =J56 -> Chocolate mass | D66: =D62-D58 -> 0 | E66: =E62-E58 -> 1.53 | F66: =F62-F58 -> 2.4 | G66: =G62-G58 -> -2.1 | J66: =J56 -> Chocolate mass | K66: =K56 -> 867156 | M66: =VLOOKUP($K66,'list of materials'!$A:$F,5,0) -> 28 | N66: =VLOOKUP($K66,'list of materials'!$A:$F,5,0) -> 28 | O66: =VLOOKUP($K66,'list of materials'!$A:$F,5,0) -> 28 | P66: =VLOOKUP($K66,'list of materials'!$A:$F,6,0) -> 31
B67: =I57 -> SFG | C67: =J57 -> Fried Peanut | D67: =D63-D59 -> 0 | E67: =E63-E59 -> -1.02 | F67: =F63-F59 -> -1.6 | G67: =G63-G59 -> 1.4 | J67: =J57 -> Fried Peanut | K67: =K57 -> 876145 | M67: =VLOOKUP($K67,'list of materials'!$A:$F,5,0) -> 28.75 | N67: =VLOOKUP($K67,'list of materials'!$A:$F,5,0) -> 28.75 | O67: =VLOOKUP($K67,'list of materials'!$A:$F,5,0) -> 28.75 | P67: =VLOOKUP($K67,'list of materials'!$A:$F,6,0) -> 27.6
B68: =I58 -> RM | C68: =J58 -> Caramel | D68: =D64-D60 -> 0 | E68: =E64-E60 -> -0.51 | F68: =F64-F60 -> -0.8 | G68: =G64-G60 -> 0.7 | J68: =J58 -> Caramel | K68: =K58 -> 765190 | M68: =VLOOKUP($K68,'list of materials'!$A:$F,5,0) -> 15 | N68: =VLOOKUP($K68,'list of materials'!$A:$F,5,0) -> 15 | O68: =VLOOKUP($K68,'list of materials'!$A:$F,5,0) -> 15 | P68: =VLOOKUP($K68,'list of materials'!$A:$F,6,0) -> 16
A70: Formulation var currency | B70: =I56 -> RM | C70: =J56 -> Chocolate mass | D70: =D66*M66 -> 0 | E70: =E66*N66 -> 42.84 | F70: =F66*O66 -> 67.2 | G70: =G66*P66 -> -65.1
B71: =I57 -> SFG | C71: =J57 -> Fried Peanut | D71: =D67*M67 -> 0 | E71: =E67*N67 -> -29.325 | F71: =F67*O67 -> -46 | G71: =G67*P67 -> 38.64
B72: =I58 -> RM | C72: =J58 -> Caramel | D72: =D68*M68 -> 0 | E72: =E68*N68 -> -7.65 | F72: =F68*O68 -> -12 | G72: =G68*P68 -> 11.2
A74: Actual consumption Qty | B74: =I56 -> RM | C74: =J56 -> Chocolate mass | D74: =-SUMIFS(Movements!$I:$I,Movements!$A:$A,D$55,Movements!$G:$G,$A$75,Movements!$C:$C,'Formulation & overusage'!$C74,Movements!$E:$E,'Formulation & overusage'!$A$76) -> 0 | E74: =-SUMIFS(Movements!$I:$I,Movements!$A:$A,E$55,Movements!$G:$G,$A$75,Movements!$C:$C,'Formulation & overusage'!$C74,Movements!$E:$E,'Formulation & overusage'!$A$76) -> 361.08 | F74: =-SUMIFS(Movements!$I:$I,Movements!$A:$A,F$55,Movements!$G:$G,$A$75,Movements!$C:$C,'Formulation & overusage'!$C74,Movements!$E:$E,'Formulation & overusage'!$A$76) -> 566.4 | G74: =-SUMIFS(Movements!$I:$I,Movements!$A:$A,G$55,Movements!$G:$G,$A$75,Movements!$C:$C,'Formulation & overusage'!$C74,Movements!$E:$E,'Formulation & overusage'!$A$76) -> 495.6
A75: C | B75: =I57 -> SFG | C75: =J57 -> Fried Peanut | D75: =-SUMIFS(Movements!$I:$I,Movements!$A:$A,D$55,Movements!$G:$G,$A$75,Movements!$C:$C,'Formulation & overusage'!$C75,Movements!$E:$E,'Formulation & overusage'!$A$76) -> 0 | E75: =-SUMIFS(Movements!$I:$I,Movements!$A:$A,E$55,Movements!$G:$G,$A$75,Movements!$C:$C,'Formulation & overusage'!$C75,Movements!$E:$E,'Formulation & overusage'!$A$76) -> 104.55 | F75: =-SUMIFS(Movements!$I:$I,Movements!$A:$A,F$55,Movements!$G:$G,$A$75,Movements!$C:$C,'Formulation & overusage'!$C75,Movements!$E:$E,'Formulation & overusage'!$A$76) -> 164 | G75: =-SUMIFS(Movements!$I:$I,Movements!$A:$A,G$55,Movements!$G:$G,$A$75,Movements!$C:$C,'Formulation & overusage'!$C75,Movements!$E:$E,'Formulation & overusage'!$A$76) -> 143.5
A76: Fint L | B76: =I58 -> RM | C76: =J58 -> Caramel | D76: =-SUMIFS(Movements!$I:$I,Movements!$A:$A,D$55,Movements!$G:$G,$A$75,Movements!$C:$C,'Formulation & overusage'!$C76,Movements!$E:$E,'Formulation & overusage'!$A$76) -> 0 | E76: =-SUMIFS(Movements!$I:$I,Movements!$A:$A,E$55,Movements!$G:$G,$A$75,Movements!$C:$C,'Formulation & overusage'!$C76,Movements!$E:$E,'Formulation & overusage'!$A$76) -> 52.02 | F76: =-SUMIFS(Movements!$I:$I,Movements!$A:$A,F$55,Movements!$G:$G,$A$75,Movements!$C:$C,'Formulation & overusage'!$C76,Movements!$E:$E,'Formulation & overusage'!$A$76) -> 81.6 | G76: =-SUMIFS(Movements!$I:$I,Movements!$A:$A,G$55,Movements!$G:$G,$A$75,Movements!$C:$C,'Formulation & overusage'!$C76,Movements!$E:$E,'Formulation & overusage'!$A$76) -> 71.4
A78: Usage variance Qty | B78: =I56 -> RM | C78: =J56 -> Chocolate mass | D78: =D74-D62 -> 0 | E78: =E74-E62 -> -1.53 | F78: =F74-F62 -> -2.4 | G78: =G74-G62 -> 0
B79: =I57 -> SFG | C79: =J57 -> Fried Peanut | D79: =D75-D63 -> 0 | E79: =E75-E63 -> 1.02 | F79: =F75-F63 -> 1.6 | G79: =G75-G63 -> 0
B80: =I58 -> RM | C80: =J58 -> Caramel | D80: =D76-D64 -> 0 | E80: =E76-E64 -> 0.51 | F80: =F76-F64 -> 0.8 | G80: =G76-G64 -> 0
A82: Usage variance currency | B82: =I56 -> RM | C82: =J56 -> Chocolate mass | D82: =D78*M66 -> 0 | E82: =E78*N66 -> -42.84 | F82: =F78*O66 -> -67.2 | G82: =G78*P66 -> 0
B83: =I57 -> SFG | C83: =J57 -> Fried Peanut | D83: =D79*M67 -> 0 | E83: =E79*N67 -> 29.325 | F83: =F79*O67 -> 46 | G83: =G79*P67 -> 0
B84: =I58 -> RM | C84: =J58 -> Caramel | D84: =D80*M68 -> 0 | E84: =E80*N68 -> 7.65 | F84: =F80*O68 -> 12 | G84: =G80*P68 -> 0
C87: P&L reconciliation | D87: October | E87: November | F87: December | G87: January
A88: Consumption @ std price from Mat movements | D88: =-SUMIFS(Movements!$K:$K,Movements!$G:$G,$I$88,Movements!$A:$A,D$87) -> 0 | E88: =-SUMIFS(Movements!$K:$K,Movements!$G:$G,$I$88,Movements!$A:$A,E$87) -> 42858.665 | F88: =-SUMIFS(Movements!$K:$K,Movements!$G:$G,$I$88,Movements!$A:$A,F$87) -> 66610.887 | G88: =-SUMIFS(Movements!$K:$K,Movements!$G:$G,$I$88,Movements!$A:$A,G$87) -> 31761.6 | I88: C
A89: Consumption @ std price from this sheet | D89: =SUMPRODUCT(D22:D24,M14:M16)+D46*M41+SUMPRODUCT(D74:D76,M66:M68) -> 0 | E89: =SUMPRODUCT(E22:E24,N14:N16)+E46*N41+SUMPRODUCT(E74:E76,N66:N68) -> 42858.665 | F89: =SUMPRODUCT(F22:F24,O14:O16)+F46*O41+SUMPRODUCT(F74:F76,O66:O68) -> 66610.887 | G89: =SUMPRODUCT(G22:G24,P14:P16)+G46*P41+SUMPRODUCT(G74:G76,P66:P68) -> 31761.6
C90: check | D90: =D89-D88 -> 0 | E90: =E89-E88 -> 0 | F90: =F89-F88 -> 0 | G90: =G89-G88 -> 0
A92: Expected consumption @std BOM | D92: =SUMPRODUCT(D6:D8,M14:M16)+SUMPRODUCT(D58:D60,M66:M68)+D38*M41 -> 0 | E92: =SUMPRODUCT(E6:E8,N14:N16)+SUMPRODUCT(E58:E60,N66:N68)+E38*N41 -> 43003.853 | F92: =SUMPRODUCT(F6:F8,O14:O16)+SUMPRODUCT(F58:F60,O66:O68)+F38*O41 -> 66610.887 | G92: =SUMPRODUCT(G6:G8,P14:P16)+SUMPRODUCT(G58:G60,P66:P68)+G38*P41 -> 31862.21
A93: Expected consumption @act BOM | D93: =SUMPRODUCT(D10:D12,M14:M16)+SUMPRODUCT(D62:D64,M66:M68)+D40*M41 -> 0 | E93: =SUMPRODUCT(E10:E12,N14:N16)+SUMPRODUCT(E62:E64,N66:N68)+E40*N41 -> 43009.717 | F93: =SUMPRODUCT(F10:F12,O14:O16)+SUMPRODUCT(F62:F64,O66:O68)+F40*O41 -> 66620.087 | G93: =SUMPRODUCT(G10:G12,P14:P16)+SUMPRODUCT(G62:G64,P66:P68)+G40*P41 -> 31846.95
A94: Actual consumption @act BOM | D94: =SUMPRODUCT(D22:D24,M14:M16)+SUMPRODUCT(D74:D76,M66:M68)+D46*M41 -> 0 | E94: =SUMPRODUCT(E22:E24,N14:N16)+SUMPRODUCT(E74:E76,N66:N68)+E46*N41 -> 42858.665 | F94: =SUMPRODUCT(F22:F24,O14:O16)+SUMPRODUCT(F74:F76,O66:O68)+F46*O41 -> 66610.887 | G94: =SUMPRODUCT(G22:G24,P14:P16)+SUMPRODUCT(G74:G76,P66:P68)+G46*P41 -> 31761.6
A96: Formulation variance | D96: =D93-D92 -> 0 | E96: =E93-E92 -> 5.865 | F96: =F93-F92 -> 9.2 | G96: =G93-G92 -> -15.26
A97: Usage variance | D97: =D94-D93 -> 0 | E97: =E94-E93 -> -151.0525 | F97: =F94-F93 -> -9.2 | G97: =G94-G93 -> -85.35
C98: check | D98: =D92+D96+D97-D94 -> 0 | E98: =E92+E96+E97-E94 -> 0 | F98: =F92+F96+F97-F94 -> 0 | G98: =G92+G96+G97-G94 -> 0
A100: Formulation var currency | B100: RM | D100: =D18+D20+D19+D44+D70+D72 -> 0 | E100: =E18+E20+E19+E44+E70+E72 -> 35.19 | F100: =F18+F20+F19+F44+F70+F72 -> 55.2 | G100: =G18+G20+G19+G44+G70+G72 -> -53.9
A101: Formulation var currency | B101: SFG | D101: =D71 -> 0 | E101: =E71 -> -29.325 | F101: =F71 -> -46 | G101: =G71 -> 38.64
C102: check | D102: =D100+D101-D96 -> 0 | E102: =E100+E101-E96 -> 1.5241142e-12 | F102: =F100+F101-F96 -> 2.692957e-12 | G102: =G100+G101-G96 -> 5.2580162e-13
A103: Usage variance currency | B103: RM | D103: =D30+D31+D32+D52+D82+D84 -> 0 | E103: =E30+E31+E32+E52+E82+E84 -> -180.3775 | F103: =F30+F31+F32+F52+F82+F84 -> -55.2 | G103: =G30+G31+G32+G52+G82+G84 -> -85.35
A104: Usage variance currency | B104: SFG | D104: =D83 -> 0 | E104: =E83 -> 29.325 | F104: =F83 -> 46 | G104: =G83 -> 0
C105: check | D105: =D103+D104-D97 -> 0 | E105: =E103+E104-E97 -> -1.1937118e-12 | F105: =F103+F104-F97 -> -2.4797941e-12 | G105: =G103+G104-G97 -> -1.1084467e-12
A106: Expected consumption @std BOM | B106: RM | D106: =D6*M14+D7*M15+D8*M16+D38*M41+D58*M66+D60*M68 -> 0 | E106: =E6*N14+E7*N15+E8*N16+E38*N41+E58*N66+E60*N68 -> 39998.04 | F106: =F6*O14+F7*O15+F8*O16+F38*O41+F58*O66+F60*O68 -> 61895.887 | G106: =G6*P14+G7*P15+G8*P16+G38*P41+G58*P66+G60*P68 -> 27940.25
A107: Expected consumption @std BOM | B107: SFG | D107: =D59*M67 -> 0 | E107: =E59*N67 -> 3005.8125 | F107: =F59*O67 -> 4715 | G107: =G59*P67 -> 3921.96
C108: check | D108: =D107+D106-D92 -> 0 | E108: =E107+E106-E92 -> 0 | F108: =F107+F106-F92 -> 0 | G108: =G107+G106-G92 -> 0

Sheet LOCOM
E2: October | F2: November | G2: December | H2: January
B3: 120301 | C3: Fint | D3: Closing stock, qty | E3: =Stocks!E23 -> 0 | F3: =Stocks!F23 -> 210 | G3: =Stocks!G23 -> 100 | H3: =Stocks!H23 -> 0
B4: 156212 | C4: Step | E4: =Stocks!E24 -> 0 | F4: =Stocks!F24 -> 500 | G4: =Stocks!G24 -> 700 | H4: =Stocks!H24 -> 0
B5: 120301 | C5: Fint | D5: Selling price | F5: =Sales!I5 -> 59 | G5: =Sales!J5 -> 63 | H5: =Sales!K5 -> 65
B6: 156212 | C6: Step | F6: =Sales!I6 -> 35 | G6: =Sales!J6 -> 25 | H6: =Sales!K6 -> 25
B7: 120301 | C7: Fint | D7: Standard cost | F7: =VLOOKUP($B7,'list of materials'!$A:$F,5,0) -> 27.24775 | G7: =VLOOKUP($B7,'list of materials'!$A:$F,5,0) -> 27.24775 | H7: =VLOOKUP($B7,'list of materials'!$A:$F,6,0) -> 29.2598
B8: 156212 | C8: Step | F8: =VLOOKUP($B8,'list of materials'!$A:$F,5,0) -> 25.945 | G8: =VLOOKUP($B8,'list of materials'!$A:$F,5,0) -> 25.945 | H8: =VLOOKUP($B8,'list of materials'!$A:$F,6,0) -> 28.45
B9: 120301 | C9: Fint | D9: LOCOM provision | F9: =IF(F5>F7,0,(F5-F7)*F3) -> 0 | G9: =IF(G5>G7,0,(G5-G7)*G3) -> 0 | H9: =IF(H5>H7,0,(H5-H7)*H3) -> 0
B10: 156212 | C10: Step | F10: =IF(F6>F8,0,(F6-F8)*F4) -> 0 | G10: =IF(G6>G8,0,(G6-G8)*G4) -> -661.5 | H10: =IF(H6>H8,0,(H6-H8)*H4) -> 0
B12: 120301 | C12: Fint | D12: P&L impact | F12: =F9-E9 -> 0 | G12: =G9-F9 -> 0 | H12: =H9-G9 -> 0
B13: 156212 | C13: Step | F13: =F10-E10 -> 0 | G13: =G10-F10 -> -661.5 | H13: =H10-G10 -> 661.5
E14: =SUM(E12:E13) -> 0 | F14: =SUM(F12:F13) -> 0 | G14: =SUM(G12:G13) -> -661.5 | H14: =SUM(H12:H13) -> 661.5

Sheet Slow moving
B1: Company accounting guidelines: | I1: Category | J1: MOH | K1: Provision, %
I2: Active | J2: <3 | K2: 0
B3: 2 | C3: number of months to calculate average sales/consumption | I3: Slow moving | J3: 3-6 | K3: 0.2
I4: Obsolete | J4: >6 | K4: 0.8
B6: Calculation
D7: Outflow, qty | H7: Average 2-months outflow | L7: Closing stock, qty
D8: October | E8: November | F8: December | G8: January | H8: October | I8: November | J8: December | K8: January | L8: October | M8: November | N8: December | O8: January
B9: 120301 | C9: Fint | D9: =Stocks!E16 -> 0 | E9: =Stocks!F16 -> -300 | F9: =Stocks!G16 -> -910 | G9: =Stocks!H16 -> -800 | I9: =(D9+E9)/2 -> -150 | J9: =(E9+F9)/2 -> -605 | K9: =(F9+G9)/2 -> -855 | L9: =Stocks!E23 -> 0 | M9: =Stocks!F23 -> 210 | N9: =Stocks!G23 -> 100 | O9: =Stocks!H23 -> 0
B10: 156212 | C10: Step | D10: =Stocks!E17 -> 0 | E10: =Stocks!F17 -> -500 | F10: =Stocks!G17 -> -1300 | G10: =Stocks!H17 -> -1003 | I10: =(D10+E10)/2 -> -250 | J10: =(E10+F10)/2 -> -900 | K10: =(F10+G10)/2 -> -1151.5 | L10: =Stocks!E24 -> 0 | M10: =Stocks!F24 -> 500 | N10: =Stocks!G24 -> 700 | O10: =Stocks!H24 -> 0
B11: 867156 | C11: Chocolate mass | D11: =Stocks!E18 -> 0 | E11: =Stocks!F18 -> -948 | F11: =Stocks!G18 -> -1454.4 | G11: =Stocks!H18 -> -678.6 | I11: =(D11+E11)/2 -> -474 | J11: =(E11+F11)/2 -> -1201.2 | K11: =(F11+G11)/2 -> -1066.5 | L11: =Stocks!E25 -> 2481 | M11: =Stocks!F25 -> 1933 | N11: =Stocks!G25 -> 578.6 | O11: =Stocks!H25 -> 0
B12: 765190 | C12: Caramel | D12: =Stocks!E19 -> 0 | E12: =Stocks!F19 -> -151 | F12: =Stocks!G19 -> -245.1 | G12: =Stocks!H19 -> -101.9 | I12: =(D12+E12)/2 -> -75.5 | J12: =(E12+F12)/2 -> -198.05 | K12: =(F12+G12)/2 -> -173.5 | L12: =Stocks!E26 -> 198 | M12: =Stocks!F26 -> 247 | N12: =Stocks!G26 -> 51.9 | O12: =Stocks!H26 -> 0
B13: 657341 | C13: Raw Peanut | D13: =Stocks!E20 -> 0 | E13: =Stocks!F20 -> -122.6925 | F13: =Stocks!G20 -> -250.8075 | G13: =Stocks!H20 -> -116 | I13: =(D13+E13)/2 -> -61.34625 | J13: =(E13+F13)/2 -> -186.75 | K13: =(F13+G13)/2 -> -183.40375 | L13: =Stocks!E27 -> 89.5 | M13: =Stocks!F27 -> 266.8075 | N13: =Stocks!G27 -> 66 | O13: =Stocks!H27 -> 0
B14: 876145 | C14: Fried Peanut | D14: =Stocks!E21 -> 0 | E14: =Stocks!F21 -> -104.55 | F14: =Stocks!G21 -> -167 | G14: =Stocks!H21 -> -143.5 | I14: =(D14+E14)/2 -> -52.275 | J14: =(E14+F14)/2 -> -135.775 | K14: =(F14+G14)/2 -> -155.25 | L14: =Stocks!E28 -> 0 | M14: =Stocks!F28 -> 5.45 | N14: =Stocks!G28 -> 43.5 | O14: =Stocks!H28 -> 0
B15: 560196 | C15: Biscuit | D15: =Stocks!E22 -> 0 | E15: =Stocks!F22 -> -340 | F15: =Stocks!G22 -> -481 | G15: =Stocks!H22 -> -98 | I15: =(D15+E15)/2 -> -170 | J15: =(E15+F15)/2 -> -410.5 | K15: =(F15+G15)/2 -> -289.5 | L15: =Stocks!E29 -> 230 | M15: =Stocks!F29 -> 390 | N15: =Stocks!G29 -> 9 | O15: =Stocks!H29 -> 0
D17: MOH, months | H17: Stock above MOH=3 (slow moving) | L17: Slow moving reserve, currency | Q17: Std cost
D18: October | E18: November | F18: December | G18: January | H18: October | I18: November | J18: December | K18: January | L18: October | M18: November | N18: December | O18: January | Q18: November
B19: 120301 | C19: Fint | E19: =M9/-I9 -> 1.4 | F19: =N9/-J9 -> 0.16528926 | G19: =O9/-K9 -> 0 | I19: =IF((M9-(-I9*3))<0,0,M9-(-I9*3)) -> 0 | J19: =IF((N9-(-J9*3))<0,0,N9-(-J9*3)) -> 0 | K19: =IF((O9-(-K9*3))<0,0,O9-(-K9*3)) -> 0 | L19: =H19*$Q19*$K$3 -> 0 | M19: =I19*$Q19*$K$3 -> 0 | N19: =J19*$Q19*$K$3 -> 0 | O19: =K19*$Q19*$K$3 -> 0 | Q19: =VLOOKUP(B19,'list of materials'!A:F,5,0) -> 27.24775
B20: 156212 | C20: Step | E20: =M10/-I10 -> 2 | F20: =N10/-J10 -> 0.77777778 | G20: =O10/-K10 -> 0 | I20: =IF((M10-(-I10*3))<0,0,M10-(-I10*3)) -> 0 | J20: =IF((N10-(-J10*3))<0,0,N10-(-J10*3)) -> 0 | K20: =IF((O10-(-K10*3))<0,0,O10-(-K10*3)) -> 0 | L20: =H20*$Q20*$K$3 -> 0 | M20: =I20*$Q20*$K$3 -> 0 | N20: =J20*$Q20*$K$3 -> 0 | O20: =K20*$Q20*$K$3 -> 0 | Q20: =VLOOKUP(B20,'list of materials'!A:F,5,0) -> 25.945
B21: 867156 | C21: Chocolate mass | E21: =M11/-I11 -> 4.0780591 | F21: =N11/-J11 -> 0.48168498 | G21: =O11/-K11 -> 0 | I21: =IF((M11-(-I11*3))<0,0,M11-(-I11*3)) -> 511 | J21: =IF((N11-(-J11*3))<0,0,N11-(-J11*3)) -> 0 | K21: =IF((O11-(-K11*3))<0,0,O11-(-K11*3)) -> 0 | L21: =H21*$Q21*$K$3 -> 0 | M21: =I21*$Q21*$K$3 -> 2861.6 | N21: =J21*$Q21*$K$3 -> 0 | O21: =K21*$Q21*$K$3 -> 0 | Q21: =VLOOKUP(B21,'list of materials'!A:F,5,0) -> 28
B22: 765190 | C22: Caramel | E22: =M12/-I12 -> 3.2715232 | F22: =N12/-J12 -> 0.26205504 | G22: =O12/-K12 -> 0 | I22: =IF((M12-(-I12*3))<0,0,M12-(-I12*3)) -> 20.5 | J22: =IF((N12-(-J12*3))<0,0,N12-(-J12*3)) -> 0 | K22: =IF((O12-(-K12*3))<0,0,O12-(-K12*3)) -> 0 | L22: =H22*$Q22*$K$3 -> 0 | M22: =I22*$Q22*$K$3 -> 61.5 | N22: =J22*$Q22*$K$3 -> 0 | O22: =K22*$Q22*$K$3 -> 0 | Q22: =VLOOKUP(B22,'list of materials'!A:F,5,0) -> 15
B23: 657341 | C23: Raw Peanut | E23: =M13/-I13 -> 4.3492063 | F23: =N13/-J13 -> 0.35341365 | G23: =O13/-K13 -> 0 | I23: =IF((M13-(-I13*3))<0,0,M13-(-I13*3)) -> 82.76875 | J23: =IF((N13-(-J13*3))<0,0,N13-(-J13*3)) -> 0 | K23: =IF((O13-(-K13*3))<0,0,O13-(-K13*3)) -> 0 | L23: =H23*$Q23*$K$3 -> 0 | M23: =I23*$Q23*$K$3 -> 413.84375 | N23: =J23*$Q23*$K$3 -> 0 | O23: =K23*$Q23*$K$3 -> 0 | Q23: =VLOOKUP(B23,'list of materials'!A:F,5,0) -> 25
B24: 876145 | C24: Fried Peanut | E24: =M14/-I14 -> 0.10425634 | F24: =N14/-J14 -> 0.32038299 | G24: =O14/-K14 -> 0 | I24: =IF((M14-(-I14*3))<0,0,M14-(-I14*3)) -> 0 | J24: =IF((N14-(-J14*3))<0,0,N14-(-J14*3)) -> 0 | K24: =IF((O14-(-K14*3))<0,0,O14-(-K14*3)) -> 0 | L24: =H24*$Q24*$K$3 -> 0 | M24: =I24*$Q24*$K$3 -> 0 | N24: =J24*$Q24*$K$3 -> 0 | O24: =K24*$Q24*$K$3 -> 0 | Q24: =VLOOKUP(B24,'list of materials'!A:F,5,0) -> 28.75
B25: 560196 | C25: Biscuit | E25: =M15/-I15 -> 2.2941176 | F25: =N15/-J15 -> 0.021924482 | G25: =O15/-K15 -> 0 | I25: =IF((M15-(-I15*3))<0,0,M15-(-I15*3)) -> 0 | J25: =IF((N15-(-J15*3))<0,0,N15-(-J15*3)) -> 0 | K25: =IF((O15-(-K15*3))<0,0,O15-(-K15*3)) -> 0 | L25: =H25*$Q25*$K$3 -> 0 | M25: =I25*$Q25*$K$3 -> 0 | N25: =J25*$Q25*$K$3 -> 0 | O25: =K25*$Q25*$K$3 -> 0 | Q25: =VLOOKUP(B25,'list of materials'!A:F,5,0) -> 25
L26: =SUM(L19:L25) -> 0 | M26: =SUM(M19:M25) -> 3336.9438 | N26: =SUM(N19:N25) -> 0 | O26: =SUM(O19:O25) -> 0
D27: P&L impact
D28: October | E28: November | F28: December | G28: January
B29: 120301 | C29: Fint | E29: =-(M19-L19) -> 0 | F29: =-(N19-M19) -> 0 | G29: =-(O19-N19) -> 0
B30: 156212 | C30: Step | E30: =-(M20-L20) -> 0 | F30: =-(N20-M20) -> 0 | G30: =-(O20-N20) -> 0
B31: 867156 | C31: Chocolate mass | E31: =-(M21-L21) -> -2861.6 | F31: =-(N21-M21) -> 2861.6 | G31: =-(O21-N21) -> 0
B32: 765190 | C32: Caramel | E32: =-(M22-L22) -> -61.5 | F32: =-(N22-M22) -> 61.5 | G32: =-(O22-N22) -> 0
B33: 657341 | C33: Raw Peanut | E33: =-(M23-L23) -> -413.84375 | F33: =-(N23-M23) -> 413.84375 | G33: =-(O23-N23) -> 0
B34: 876145 | C34: Fried Peanut | E34: =-(M24-L24) -> 0 | F34: =-(N24-M24) -> 0 | G34: =-(O24-N24) -> 0
B35: 560196 | C35: Biscuit | E35: =-(M25-L25) -> 0 | F35: =-(N25-M25) -> 0 | G35: =-(O25-N25) -> 0
D36: =SUM(D29:D35) -> 0 | E36: =SUM(E29:E35) -> -3336.9438 | F36: =SUM(F29:F35) -> 3336.9438 | G36: =SUM(G29:G35) -> 0
